Workbook

Sheet Autocall
B1: SE0006993184 | C1: FI4000053178 | D1: SE0006261947 | E1: SE0006993192 | F1: XS1311310384 | G1: XS1322968394 | H1: SE0004575314 | I1: FI4000149547 | J1: XS1311310384 | K1: SE0005366390 | L1: FI4000177118 | M1: SE0005506029 | N1: SE0008587455
B2: 100/80/60 flat | C2: 100/80/60 memory | D2: 100/100/60 memory | E2: 100/100/60 | F2: 100/100 flat Capital Protected | G2: 100/80/60 flat coupon paid at call | H2: 100/100/60 memory | I2: 100/100/150 memory | J2: 100/100 memory Capital Protected | K2: 100/60/60 memory on call, flat on coupon barrier | L2: 100/80/60 memory | M2: 100/60/60 memory | N2: 100/100/60 flat
B3: Autocall 1 | C3: Autocall 2 | D3: Autocall 3 | E3: Autocall 4 | F3: Autocall 5 | G3: Autocall 6 | H3: Autocall 7 | I3: Autocall 8 | J3: Autocall 9 | K3: Autocall 10 | L3: Autocall 11 | M3: Autocall 12 | N3: Autocall 13
A4: Level 1 | B4: Autocall | C4: Autocall | D4: Autocall | E4: Autocall | F4: Autocall | G4: Autocall | H4: Autocall | I4: Autocall | J4: Autocall | K4: Autocall | L4: Autocall | M4: Autocall | N4: Autocall
A5: Level 2 | B5: Worst of | C5: Worst of | D5: Worst of | E5: Worst of | F5: Worst of | G5: Worst of | H5: Single underlying | I5: Single underlying FX | J5: Worst of | K5: Worst of | L5: Single underlying | M5: Worst of | N5: Worst of
A6: Level 3 | B6: Flat coupon | C6: Memory coupon | D6: Classic autocall | E6: Two coupons | F6: Flat coupon | G6: Flat coupon, accrued and paid on call or maturity | H6: Classic autocall | I6: Memory coupon | J6: Memory coupon | K6: Two coupons | L6: Memory coupon | M6: Memory coupon | N6: Flat coupon
A7: Level 4 | D7: Memory coupon | F7: Capital guaranteed | H7: Memory coupon | J7: Capital guaranteed
A8: Short description | B8: This is an autocallable with more than one underlying asset. It has a call barrier and a coupon barrier, which are at different levels, and a risk barrier. The coupon is flat, no memory. | C8: This is an autocallable with more than one underlying asset. It has a call barrier and a coupon barrier at different levels, and a risk barrier. The coupon is a memory coupon. | D8: This is an autocallable with more than one underlying asset. It has a call barrier and a coupon barrier, which are at the same level, and a risk barrier. The coupon is a memory coupon. | E8: This is an autocallable with more than one underlying asset. It has a call barrier and a coupon barrier, which are at the same level, and a risk barrier. There are two coupons, one guaranteed and one call coupon. | F8: This is a capital protected autocallable with more than one underlying asset. It has a call barrier and a coupon barrier with the same level. The coupon is flat, no memory. | G8: This is an autocallable with more than one underlying asset. It has a call barrier and a coupon barrier at different levels, and a risk barrier. The coupon(s) will be accrued and paid at call. | H8: This is an autocallable with one underlying asset. It has a call barrier and a coupon barrier at the same level, and a risk barrier. The coupon is a memory coupon. | I8: This is an autocallable with one underlying asset (currency pair). It has a call barrier and a coupon barrier at the same level, and a risk barrier on a higher level. The coupon is a memory coupon. | J8: This is a capital protected autocallable with more than one underlying asset. It has a call barrier and a coupon barrier at the same level. The coupon is a memory coupon. | K8: This is an autocallable with more than one underlying asset. It has a call barrier and a coupon barrier at different levels, and a risk barrier. There are two coupons, one flat coupon paid when the worst performing underlying asset is at or above the coupon barrier, but below the call barrier. And one memory coupon (call coupon) paid when all underlying assets are at or above the call barrier. | L8: This is an autocallable with one underlying asset. It has a call barrier and a coupon barrier on different levels, and a risk barrier. The coupon is a memory coupon. | M8: This is an autocallable with more than one underlying asset. It has a call barrier and a coupon barrier at different levels, and a risk barrier. The coupon is a memory coupon. | N8: This is an autocallable with more than one underlying asset. It has a call barrier and a coupon barrier, which are at the same level, and a risk barrier. The coupon is a flat coupon.
A9: EUSIPA-code | B9: 1260 | C9: 1260 | D9: 1260 | E9: 1260 | F9: 1260 | G9: 1260 | H9: 1260 | I9: 1260 | J9: 1260 | K9: 1260 | L9: 1260 | M9: 1260 | N9: 1260
A10: JIRA Code
A11: JIRA Issue ID
A12: JIRA Product Feature | B12: EDIP | C12: EDIP | D12: EDIP | E12: EDIP | F12: 100%CapProtected | G12: EDIP | H12: EDIP | I12: EDIP | J12: 100%CapProtected | K12: EDIP | L12: EDIP | M12: EDIP | N12: EDIP
A13: JIRA Product Feature | B13: DigitalObs | C13: DigitalObs Memory | D13: DigitalObs Memory | E13: DigitalObs Zero | F13: DigitalObs Coupon | G13: DigitalObs CouponAccrued | H13: DigitalObs Memory | I13: DigitalObs Memory | J13: DigitalObs Coupon | K13: DigitalObs Coupon | L13: DigitalObs Memory | M13: DigitalObs Memory | N13: DigitalObs Coupon
A14: JIRA Product Feature | B14: CallObs Zero | C14: CallObs Zero | D14: CallObs Zero | E14: CallObs Coupon | F14: CallObs Zero | G14: CallObs Zero | H14: CallObs Zero | I14: CallObs Zero | J14: CallObs Zero | K14: CallObs xN | L14: CallObs Zero | M14: CallObs Zero | N14: CallObs Zero
A15: JIRA Product Feature | E15: FixedCoupons | G15: Special
A16: Fixing needed? | B16: FinalFixing, DigitalObsFixing, CallObsFixing | C16: FinalFixing, DigitalObsFixing, CallObsFixing | D16: FinalFixing, DigitalObsFixing, CallObsFixing | E16: FinalFixing, DigitalObsFixing, CallObsFixing | F16: FinalFixing, DigitalObsFixing, CallObsFixing | G16: FinalFixing, DigitalObsFixing, CallObsFixing | H16: FinalFixing, DigitalObsFixing, CallObsFixing | I16: FinalFixing, DigitalObsFixing, CallObsFixing | J16: FinalFixing, DigitalObsFixing, CallObsFixing | K16: FinalFixing, DigitalObsFixing, CallObsFixing | L16: FinalFixing, DigitalObsFixing, CallObsFixing | M16: FinalFixing, DigitalObsFixing, CallObsFixing | N16: FinalFixing, DigitalObsFixing, CallObsFixing
A19: Type | B19: Express certificate (Autocall) 1 b according to the MiFID (legal form?) | C19: Express certificate (Autocall) 1 b according to the MiFID (legal form?) | D19: Express certificate (Autocall) 1 b according to the MiFID (legal form?) | E19: Express certificate (Autocall) 1 b according to the MiFID (legal form?) | F19: Express certificate (Autocall) 1 b according to the MiFID (legal form?) | G19: Express certificate (Autocall) 1 b according to the MiFID (legal form?) | H19: Express certificate (Autocall) 1 b according to the MiFID (legal form?) | I19: Express certificate (Autocall) 1 b according to the MiFID (legal form?) | J19: Express certificate (Autocall) 1 b according to the MiFID (legal form?) | K19: Express certificate (Autocall) 1 b according to the MiFID (legal form?) | L19: Express certificate (Autocall) 1 b according to the MiFID (legal form?) | M19: Express certificate (Autocall) 1 b according to the MiFID (legal form?) | N19: Express certificate (Autocall) 1 b according to the MiFID (legal form?)
B20: Underlying asset(s) (initial price) | C20: Underlying asset(s) (initial price) | D20: Underlying asset(s) (initial price) | E20: Underlying asset(s) (initial price) | F20: Underlying asset(s) (initial price) | G20: Underlying asset(s) (initial price) | H20: Underlying asset(s) (initial price) | I20: Underlying asset(s) (initial price) | J20: Underlying asset(s) (initial price) | K20: Underlying asset(s) (initial price) | L20: Underlying asset(s) (initial price) | M20: Underlying asset(s) (initial price) | N20: Underlying asset(s) (initial price)
A21: How the investment works | B21: The objective is to receive a coupon, even if the worst performing underlying asset remains unchanged or even has a slightly negative performance. | C21: The objective is to receive a coupon, even if the worst performing underlying asset remains unchanged or even has a slightly negative performance. | D21: The objective is to receive a coupon, even if the worst performing underlying asset remains unchanged or even has a slightly negative performance. | E21: The objective is to receive a coupon, even if the worst performing underlying asset remains unchanged or even has a slightly negative performance. | F21: The objective is to receive a coupon, even if the worst performing underlying asset remains unchanged or even has a slightly negative performance. | G21: The objective is to receive a coupon, even if the worst performing underlying asset remains unchanged or even has a slightly negative performance. | H21: The objective is to receive a coupon, even if the underlying asset remains unchanged or even has a slightly negative performance. | I21: The objective is to receive a coupon, even if the underlying asset remains unchanged or even has a slightly positive performance. | J21: The objective is to receive a coupon, even if the worst performing underlying asset remains unchanged or even has a slightly negative performance. | K21: The objective is to receive a coupon, even if the worst performing underlying asset remains unchanged or even has a slightly negative performance. | L21: The objective is to receive a coupon, even if the underlying asset remains unchanged or even has a slightly negative performance. | M21: The objective is to receive a coupon, even if the worst performing underlying asset remains unchanged or even has a slightly negative performance. | N21: The objective is to receive a coupon, even if the worst performing underlying asset remains unchanged or even has a slightly negative performance.
B22: The return of the investment depends on the performance of the worst performing underlying asset during the lifetime of the investment. | C22: The return of the investment depends on the performance of the worst performing underlying asset during the lifetime of the investment. | D22: The return of the investment depends on the performance of the worst performing underlying asset during the lifetime of the investment. | E22: The return of the investment depends on the performance of the worst performing underlying asset during the lifetime of the investment. | F22: The return of the investment depends on the performance of the worst performing underlying asset during the lifetime of the investment. | G22: The return of the investment depends on the performance of the worst performing underlying asset during the lifetime of the investment. | H22: The return of the investment depends on the performance of the underlying asset during the lifetime of the investment. | I22: The return of the investment depends on the performance of the underlying asset during the lifetime of the investment. | J22: The return of the investment depends on the performance of the worst performing underlying asset during the lifetime of the investment. | K22: The return of the investment depends on the performance of the worst performing underlying asset during the lifetime of the investment. | L22: The return of the investment depends on the performance of the underlying asset during the lifetime of the investment. | M22: The return of the investment depends on the performance of the worst performing underlying asset during the lifetime of the investment. | N22: The return of the investment depends on the performance of the worst performing underlying asset during the lifetime of the investment.
B23: If, on an observation date, all underlying assets are at or above the call barrier the note will redeem early and the nominal amount plus a coupon will be paid on the early redemption date immediately following the observation date. | C23: If, on an observation date, all underlying assets are at or above the call barrier the note will redeem early and the nominal amount plus a coupon for each observation date that has passed and not previously paid any coupon will be paid on the early redemption date immediately following the observation date. | D23: If, on an observation date, all underlying assets are at or above the call barrier and the coupon barrier the note will redeem early and the nominal amount plus a coupon for each observation date that has passed will be paid on the early redemption date immediately following the observation date. | E23: If, on an observation date, all underlying assets are at or above the call barrier and the coupon barrier the note will redeem early and the nominal amount, the guaranteed coupon and a call coupon will be paid on the early redemption date immediately following the observation date. | F23: If, on an observation date, all underlying assets are at or above the call barrier and the coupon barrier the note will redeem early and the nominal amount plus a coupon will be paid on the early redemption date immediately following the observation date. | G23: If, on an observation date, all underlying assets are at or above the call barrier the note will redeem early and the nominal amount plus a coupon for each valuation date that has passed where all underlying assets has been at or above the coupon barrier, will be paid on the early redemption date immediately following the observation date. | H23: If, on an observation date, the underlying asset is at or above the call barrier and the coupon barrier the note will redeem early and the nominal amount plus a coupon for each observation date that has passed will be paid on the early redemption date immediately following the observation date. | I23: If, on an observation date, the underlying asset is at or below the call barrier and the coupon barrier the note will redeem early and the nominal amount plus a coupon for each observation date that has passed will be paid on the early redemption date immediately following the observation date. | J23: If, on an observation date, all underlying assets are at or above the call barrier and the coupon barrier the note will redeem early and the nominal amount plus a coupon for each observation date that has passed will be paid on the early redemption date immediately following the observation date. | K23: If, on an observation date, all underlying assets are at or above the call barrier the note will redeem early and the nominal amount plus a call coupon for each observation date that has passed will be paid on the early redemption date immediately following the observation date. | L23: If, on an observation date, the underlying asset is at or above the call barrier the note will redeem early and the nominal amount plus a coupon for each observation date that has passed and not previously paid any coupon will be paid on the early redemption date immediately following the observation date. | M23: If, on an observation date, all underlying assets are at or above the call barrier the note will redeem early and the nominal amount plus a coupon for each observation date that has passed and not previously paid any coupon will be paid on the early redemption date immediately following the observation date. | N23: If, on an observation date, all underlying assets are at or above the call barrier and the coupon barrier the note will redeem early and the nominal amount plus a coupon will be paid on the early redemption date immediately following the observation date.
B24: If, on a valuation date, the worst performing underlying asset is at or above the coupon barrier, but below the call barrier, a coupon will be paid on the next interest payment date. The note will not redeem and the maturity will extend at least to the next early redemption date. | C24: If, on a valuation date, the worst performing underlying asset is at or above the coupon barrier, but below the call barrier, a coupon for each valuation date that has passed and not previously paid any coupon will be paid on the next interest payment date. The note will not redeem and the maturity will extend at least to the next early redemption date. | D24: If, on a observation date, the worst performing underlying asset is below the call barrier and the coupon barrier, the note will not redeem and the maturity will extend at least to the next early redemption date. | E24: If, on an observation date, the worst performing underlying asset is below the call barrier and the coupon barrier the note will pay the guaranteed coupon. The note will not redeem and the maturity will extend at least to the next early redemption date. | F24: If, on an observation date, the worst performing underlying asset is below the call barrier and the coupon barrier the note will not redeem and the maturity will extend at least to the next early redemption date without paying any coupon. | G24: If, on a valuation date, the worst performing underlying asset is at or above the coupon barrier, but below the call barrier, a coupon will be recorded. The coupon will be paid when the note is redeemed, at the redemption date at the latest. | H24: If, on an observation date, the underlying asset is below the call barrier and the coupon barrier the note will not redeem and the maturity will extend at least to the next early redemption date. | I24: If, on an observation date, the underlying asset is above the call barrier and the coupon barrier the note will not redeem and the maturity will extend at least to the next early redemption date. | J24: If, on an observation date, the worst performing underlying asset is below the call barrier and the coupon barrier the note will not redeem and the maturity will extend at least to the next early redemption date. | K24: If, on a valuation date, the worst performing underlying asset is at or above the coupon barrier, but below the call barrier, the note will pay a flat coupon. The note will not redeem and the maturity will extend at least to the next early redemption date. | L24: If, on a valuation date, the underlying asset is at or above the coupon barrier, but below the call barrier, a coupon for each valuation date that has passed and not previously paid any coupon will be paid on the next interest payment date. The note will not redeem and the maturity will extend at least to the next early redemption date. | M24: If, on a valuation date, the worst performing underlying asset is at or above the coupon barrier, but below the call barrier, a coupon for each valuation date that has passed and not previously paid any coupon will be paid on the next interest payment date. The note will not redeem and the maturity will extend at least to the next early redemption date. | N24: If, on a observation date, the worst performing underlying asset is below the call barrier and the coupon barrier, the note will not redeem and the maturity will extend at least to the next early redemption date.
B25: If, on a valuation date, the worst performing underlying asset is below both the call barrier and the coupon barrier, the note will not redeem and the maturity will extend at least to the next early redemption date without paying any coupon. | C25: If, on a valuation date, the worst performing underlying asset is below both the call barrier and the coupon barrier, the note will not redeem and the maturity will extend at least to the next early redemption date. | D25: On the last observation date there are three possible scenarios: 1. All underlying assets are at or above the call barrier and the coupon barrier. The note will then pay the nominal amount plus a coupon for each observation date that has passed, on the redemption date. 2. The worst performing underlying asset is below the call barrier and the coupon barrier, but at or above the risk barrier. The note will then pay the nominal amount on the redemption date. 3. The worst performing underlying asset is below the risk barrier. The note will then pay the nominal amount reduced by the negative performance of the worst performing underlying asset, on the redemption date. | E25: On the last observation date there are three possible scenarios: 1. All underlying assets are at or above the call barrier and the coupon barrier. The note will then pay the nominal amount, the guaranteed coupon and a call coupon on the redemption date. 2. The worst performing underlying asset is below the call barrier and the coupon barrier, but at or above the risk barrier. The note will then pay the nominal amount and the guaranteed coupon on the redemption date. 3. The worst performing underlying asset is below the risk barrier. The note will then pay the nominal amount, reduced by the negative performance of the worst performing underlying asset, and the guaranteed coupon on the redemption date. | F25: On the last observation date there are two possible scenarios: 1. All underlying assets are at or above the coupon barrier and the call barrier. The note will then pay the nominal amount plus a coupon on the redemption date. 2. The worst performing underlying asset has a negative performance. The note will then pay the nominal amount on the redemption date. | G25: If, on a valuation date, the worst performing underlying asset is below both the call barrier and the coupon barrier, no coupon will be credited. | H25: On the last observation date there are three possible scenarios: 1. The underlying asset is at or above the call barrier and the coupon barrier. The note will then pay the nominal amount plus a coupon for each observation date that has passed and not previously paid any coupon on the redemption date. 2. The underlying asset is below the call barrier and the coupon barrier, but at or above the risk barrier. The note will then pay the nominal amount on the redemption date. 3. The underlying asset is below the risk barrier. The note will then pay the nominal amount reduced by the negative performance of the underlying asset, on the redemption date. | I25: If, on the last observation date, the underlying asset is above the risk barrier the note will pay less than the nominal amount. | J25: On the last observation date there are two possible scenarios: 1. All underlying assets are at or above the coupon barrier and the call barrier. The note will then pay the nominal amount plus a coupon for each observation date that has passed on the redemption date. 2. The worst performing underlying asset has a negative performance. The note will then pay the nominal amount on the redemption date. | K25: If, on a valuation date, the worst performing underlying asset is below both the call barrier and the coupon barrier, the note will not redeem and the maturity will extend at least to the next early redemption date without paying any flat coupon. | L25: If, on a valuation date, the underlying asset is below both the call barrier and the coupon barrier, the note will not redeem and the maturity will extend at least to the next early redemption date. | M25: If, on a valuation date, the worst performing underlying asset is below both the call barrier and the coupon barrier, the note will not redeem and the maturity will extend at least to the next early redemption date. | N25: On the last observation date there are three possible scenarios: 1. All underlying assets are at or above the call barrier and the coupon barrier. The note will then pay the nominal amount plus a coupon on the redemption date. 2. The worst performing underlying asset is below the call barrier and the coupon barrier, but at or above the risk barrier. The note will then pay the nominal amount on the redemption date. 3. The worst performing underlying asset is below the risk barrier. The note will then pay the nominal amount reduced by the negative performance of the worst performing underlying asset, on the redemption date.
B26: On the last observation date there are three possible scenarios: 1. All underlying assets are at or above the coupon barrier. The note will then pay the nominal amount plus a coupon on the redemption date. 2. The worst performing underlying asset is below the coupon barrier, but at or above the risk barrier. The note will then pay the nominal amount on the redemption date. 3. The worst performing underlying asset is below the risk barrier. The note will then pay the nominal amount reduced by the negative performance of the worst performing underlying asset, on the redemption date. | C26: On the last observation date there are three possible scenarios: 1. All underlying assets are at or above the coupon barrier. The note will then pay the nominal amount plus a coupon for each observation dvaluation date that has passed and not previously paid any coupon, on the redemption date. 2. The worst performing underlying asset is below the coupon barrier, but at or above the risk barrier. The note will then pay the nominal amount on the redemption date. 3. The worst performing underlying asset is below the risk barrier. The note will then pay the nominal amount reduced by the negative performance of the worst performing underlying asset, on the redemption date. | G26: On the last observation date there are three possible scenarios: 1. All underlying assets are at or above the coupon barrier. The note will then pay the nominal amount plus a coupon for the last period and for each valuation date that has passed where all underlying assets has been at or above the coupon barrier, on the redemption date. 2. The worst performing underlying asset is below the coupon barrier, but at or above the risk barrier. The note will then pay the nominal amount plus a coupon for each valuation date that has passed where all underlying assets has been at or above the coupon barrier, on the redemption date. 3. The worst performing underlying asset is below the risk barrier. The note will then pay the nominal amount, reduced by the negative performance of the worst performing underlying asset, plus a coupon for each valuation date that has passed where all underlying assets has been at or above the coupon barrier, on the redemption date. | K26: On the last observation date there are three possible scenarios: 1. All underlying assets are at or above the call barrier. The note will then pay the nominal amount plus a call coupon for each observation date that has passed, on the redemption date. 2. The worst performing underlying asset is below the call barrier, but at or above the coupon barrier. The note will then pay the nominal amount plus a flat coupon on the redemption date. 3. The worst performing underlying asset is below the risk barrier. The note will then pay the nominal amount reduced by the negative performance of the worst performing underlying asset on the redemption date. | L26: On the last observation date there are three possible scenarios: 1. The underlying asset is at or above the coupon barrier. The note will then pay the nominal amount plus a coupon for each observation date that has passed and not previously paid any coupon on the redemption date. 2. The underlying asset is below the coupon barrier, but at or above the risk barrier. The note will then pay the nominal amount on the redemption date. 3. The underlying asset is below the risk barrier. The note will then pay the nominal amount reduced by the negative performance of the underlying asset on the redemption date. | M26: On the last observation date there are two possible scenarios: 1. All underlying assets are at or above the risk barrier. The note will then pay the nominal amount plus a coupon for each observation date that has passed and not previously paid any coupon, on the redemption date. 2. The worst performing underlying asset is below the risk barrier. The note will then pay the nominal amount reduced by the negative performance of the worst performing underlying asset on the redemption date.
A28: Key numbers:
B29: Minimum subscription amount | C29: Minimum subscription amount | D29: Minimum subscription amount | E29: Minimum subscription amount | F29: Minimum subscription amount | G29: Minimum subscription amount | H29: Minimum subscription amount | I29: Minimum subscription amount | J29: Minimum subscription amount | K29: Minimum subscription amount | L29: Minimum subscription amount | M29: Minimum subscription amount | N29: Minimum subscription amount
B30: Subscription end date | C30: Subscription end date | D30: Subscription end date | E30: Subscription end date | F30: Subscription end date | G30: Subscription end date | H30: Subscription end date | I30: Subscription end date | J30: Subscription end date | K30: Subscription end date | L30: Subscription end date | M30: Subscription end date | N30: Subscription end date
B31: Issue price | C31: Issue price | D31: Issue price | E31: Issue price | F31: Issue price | G31: Issue price | H31: Issue price | I31: Issue price | J31: Issue price | K31: Issue price | L31: Issue price | M31: Issue price | N31: Issue price
B32: Issue date | C32: Issue date | D32: Issue date | E32: Issue date | F32: Issue date | G32: Issue date | H32: Issue date | I32: Issue date | J32: Issue date | K32: Issue date | L32: Issue date | M32: Issue date | N32: Issue date
B33: Nominal amount + currency | C33: Nominal amount + currency | D33: Nominal amount + currency | E33: Nominal amount + currency | F33: Nominal amount/Capital protection + currency | G33: Nominal amount + currency | H33: Nominal amount + currency | I33: Nominal amount + currency | J33: Nominal amount/Capital protection + currency | K33: Nominal amount + currency | L33: Nominal amount + currency | M33: Nominal amount + currency | N33: Nominal amount + currency
B34: Coupon | C34: Coupon | D34: Coupon | E34: Guaranteed coupon | F34: Coupon | G34: Coupon | H34: Coupon | I34: Coupon | J34: Coupon | K34: Call coupon | L34: Coupon | M34: Coupon | N34: Coupon
B35: Call barrier | C35: Call barrier | D35: Call barrier | E35: Call coupon | F35: Call barrier | G35: Call barrier | H35: Call barrier | I35: Call barrier | J35: Call barrier | K35: Flat coupon | L35: Call barrier | M35: Call barrier | N35: Call barrier
B36: Coupon barrier | C36: Coupon barrier | D36: Coupon barrier | E36: Coupon barrier | F36: Coupon barrier | G36: Coupon barrier | H36: Coupon barrier | I36: Coupon barrier | J36: Coupon barrier | K36: Call barrier | L36: Coupon barrier | M36: Coupon barrier | N36: Coupon barrier
B37: Risk barrier | C37: Risk barrier | D37: Risk barrier | E37: Call barrier | F37: Observation date(s) | G37: Risk barrier | H37: Risk barrier | I37: Risk barrier | J37: Observation date(s) | K37: Coupon barrier | L37: Risk barrier | M37: Risk barrier | N37: Risk barrier
B38: Observation date(s) | C38: Observation date(s) | D38: Observation date(s) | E38: Risk barrier | F38: Early redemption date(s) | G38: Observation date(s) | H38: Observation date(s) | I38: Observation date(s) | J38: Early redemption date(s) | K38: Risk barrier | L38: Observation date(s) | M38: Observation date(s) | N38: Observation date(s)
B39: Valuation date(s) | C39: Valuation date(s) | D39: Early redemption date(s) | E39: Observation date(s) | F39: Redemption date | G39: Valuation date(s) | H39: Early redemption date(s) | I39: Early redemption date(s) | J39: Redemption date | K39: Observation date(s) | L39: Valuation date(s) | M39: Valuation date(s) | N39: Early redemption date(s)
B40: Early redemption date(s) | C40: Early redemption date(s) | D40: Redemption date | E40: Early redemption date(s) | G40: Early redemption date(s) | H40: Redemption date | I40: Redemption date | K40: Valuation date(s) | L40: Early redemption date(s) | M40: Early redemption date(s) | N40: Redemption date
B41: Interest payment date(s) | C41: Interest payment date(s) | E41: Redemption date | G41: Redemption date | K41: Early redemption date(s) | L41: Interest payment date(s) | M41: Interest payment date(s)
B42: Redemption date | C42: Redemption date | I42: Initial valuation date | J42: Initial valuation date | K42: Redemption date | L42: Redemption date | M42: Redemption date
D43: Initial valuation date | E43: Initial valuation date | F43: Initial valuation date | G43: Initial valuation date | H43: Initial valuation date | N43: Initial valuation date
C44: Initial valuation date | K44: Initial valuation date | L44: Initial valuation date | M44: Initial valuation date
B45: Initial valuation date

Sheet Capital protected
B1: SE0006261657 | C1: SE0006992608 | D1: SE0006261970 | E1: FI4000090683 | F1: FI4000040530 | G1: SE0005472099 | H1: SE0005130960 | I1: SE0004391241 KP 45, bäst av tre | J1: SE0007665450 | K1: SE0005506136 | M1: DK0030344965 | N1: NONE OUTSTANDING - REMOVE | O1: FI4000069919 | P1: SE0005796281 - KP71 | R1: FI4000041280 | S1: DK0030334495 | T1: FI4000040522 | U1: FI4000040365 | V1: SE0004548204 | W1: DK0030297197 | X1: SE0004724904 | Y1: DK0030317722 | Z1: SE0006992400 | AA1: DK0030302377 | AB1: SE0005795861 | AD1: SE0005505906 | AE1: SE0004491066 | AF1: SE0005126232 | AG1: XS1344758468 | AH1: XS1241177390 | AI1: SE0006262291 | AJ1: SE0005224227 | AK1: FI4000033949 | AL1: FI4000040381 | AM1: FI4000041694 | AN1: FI4000046289 | AO1: REMOVE | AP1: REMOVE
B2: Capital protected 1 | C2: Capital protected 2 | D2: Capital protected 3 | E2: Capital protected 4 | F2: Capital protected 5 | G2: Capital protected 6 | H2: Capital protected 7 | I2: Capital protected 8 | J2: Capital protected 9 | K2: Capital protected 10 | L2: Capital protected 11 | M2: Capital protected 12 | N2: Capital protected 13 | O2: Capital protected 14 | P2: Capital protected 15 | Q2: Capital protected 16 | R2: Capital protected 17 | S2: Capital protected 18 | T2: Capital protected 19 | U2: Capital protected 20 | V2: Capital protected 21 | W2: Capital protected 22 | X2: Capital protected 23 | Y2: Capital protected 24 | Z2: Capital protected 26 | AA2: Capital protected 27 | AB2: Capital protected 28 | AC2: Capital protected 29 | AD2: Capital protected 30 | AE2: Capital protected 31 | AF2: Capital protected 32 | AG2: Capital protected 33 | AH2: Capital protected 34 | AI2: Capital protected 35 | AJ2: Capital protected 36 | AK2: Capital protected 37 | AL2: Capital protected 38 | AM2: Capital protected 39 | AN2: Capital protected 40 | AO2: Capital protected 41 | AP2: Capital protected 42
A3: Level 1 | B3: Multi underlying | C3: Multi underlying | D3: Multi underlying with best replacement | E3: Multi underlying with best replacement | F3: Multi underlying | G3: Multi underlying | H3: Single underlying | I3: Multi underlying, best performance | J3: Multi underlying with best replacement structure | K3: Single underlying, TOM | L3: Single underlying, TOM | M3: Multi underlying, underlying performance is the difference between performance in two different underlying assets | N3: Single underlying, TOM | O3: Multi underlying FX | P3: Multi underlying FX | Q3: Multi underlying | R3: Single underlying (rate) | S3: Multi underlying, relative difference betweeen two assets | T3: Single underlying (interest rate) | U3: Single underlying (interest rate) | V3: Single underlying (interest rate) | W3: Single underlying | X3: Multi underlying (relative difference between two underlying assets) | Y3: Multi underlying (relative difference between two underlying assets) | Z3: Single underlying | AA3: Single underlying | AB3: Single underlying | AC3: Single underlying | AD3: Multi underlying | AE3: Multi underlying, TOM | AF3: Single underlying, monthly performance | AG3: Multi underlying (relative difference between two underlying assets) | AH3: Multi underlying (relative difference between two underlying assets) | AI3: Multi underlying FX | AJ3: Single underlying | AK3: Single underlying (interest rate) | AL3: Single underlying (rate) | AM3: Single underlying (interest rate) | AN3: Single underlying (interest rate) | AO3: Multi underlying with best replacement | AP3: Multi underlying (relative difference between two underlying assets)
A4: Level 2 | B4: Participation ratio | C4: Participation ratio | D4: Participation ratio | E4: Participation ratio | F4: Participation ratio | G4: Capped coupon | H4: Participation ratio | I4: Participation ratio | J4: Participation ratio | K4: Participation ratio | L4: Participation ratio | M4: Participation ratio | N4: Participation ratio | O4: Participation ratio | P4: Participation ratio | Q4: Participation ratio | R4: Interest, accrued and paid at redemption | S4: Participation ratio | T4: Fixed interest rate. Accrued, acumulated and paid at redemption | U4: Floating interest | V4: Floating interest | W4: Fixed coupon | X4: Fixed coupon for a set number of interest payment dates | Y4: Participation ratio | Z4: Participation ratio | AA4: Participation ratio | AB4: Participation ratio | AC4: Participation ratio | AD4: Participation ratio | AE4: Participation ratio | AF4: Capped (monthly) + lock-in | AG4: Fixed interest for a set number of interest payment dates | AH4: Floating interest | AI4: Participation ratio | AJ4: Participation ratio | AK4: Floating interest | AL4: Interest, accrued and paid at redemption | AM4: Floating interest | AN4: Fixed interest for a set number of interest payment dates | AO4: Participation ratio | AP4: Fixed interest for a set number of interest payment dates
A5: Level 3 | B5: Flexo | C5: Quanto | D5: Flexo | E5: Quanto | F5: Capped | G5: Quanto | H5: Quanto | I5: Quanto | J5: Quanto | K5: Flexo | M5: Quanto | N5: Capped (monthly) + lock-in | O5: Quanto | P5: Best of | Q5: Capped on basket level | R5: Floor and cap | S5: Floor and cap | U5: Cap | V5: Floor and cap | W5: Floor and cap | X5: Floating interest for the forthcoming interest payment dates | Y5: Fixed interest | Z5: Flexo | AA5: Fixed coupon(Guaranteed, paid on each interest payment date) | AB5: Fixed coupon(Guaranteed) paid at maturity | AC5: Fixed coupon(Guaranteed) paid at maturity | AD5: Fixed coupon(Guaranteed) paid on each interest payment date | AE5: Quanto | AF5: Quanto | AG5: Floating interest for the forthcoming interest payment dates | AH5: Floor and cap - CMS spread | AI5: Rainbow | AJ5: Fixed coupon(Guaranteed, paid on each interest payment date) | AK5: Floor and cap | AL5: Cap | AM5: Floor and cap | AN5: Floating interest for the forthcoming interest payment dates | AO5: Quanto | AP5: Floating interest for the forthcoming interest payment dates
A6: Level 4 | F6: Quanto | L6: Quanto | N6: Quanto | P6: Quanto | Q6: Quanto | Y6: Floor and cap - CMS spread | AA6: Flexo | AB6: Flexo | AC6: Quanto | AD6: Quanto | AG6: Floor and cap - CMS spread | AI6: Quanto | AJ6: Quanto | AN6: Floor and cap | AP6: Barrier
A7: Short description | B7: This is a capital protected note with more than one underlying asset in a basket. The note is affected by currency fluctuations. | C7: This is a capital protected note with more than one underlying asset in a basket. | D7: This is a capital protected note with more than one underlying asset in a basket. When calculating the basket performance, a specified number of the best performing underlying assets in the basket will be given a fixed performance each. The note is affected by currency fluctuations. | E7: This is a capital protected note with more than one underlying asset in a basket. When calculating the basket performance, a specified number of the best performing underlying assets in the basket will be given a fixed performance each. | F7: This is a capital protected note with more than one underlying asset in a basket. When calculating the basket performance, each underlying asset has a cap. | G7: This is a capital protected note with a basket of underlying assets. If the underlying basket has a positive performance a coupon will be paid. There is a cap on the coupon. | H7: This is a capital protected note with one underlying asset. | I7: This is a capital protected note with more than one underlying asset in different baskets. At maturity the calculated returns for all the baskets is ranked. The best performer is then applied in order to calculate the return. | J7: This is a capital protected note with more than one underlying asset in a basket. When calculating the basket performance, a specified number of the best performing underlying assets in the basket will be given a fixed performance each. For a specific basket performance range, the note will pay the nominal amount plus the nominal amount multiplied by a fixed predefined coupon. For any basket performance above that range, the note will pay the nominal amount plus the nominal amount multiplied by the performance of the basket multiplied by the participation ratio on the redemption date. | K7: This is a capital protected note with one underlying asset. The performance of the underlying asset is determined by a predefined strategy – turn of the month. Turn of the month means that the note is exposed to the underlying asset only during a predefined number of days per month. The note is affected by currency fluctuations. | L7: This is a capital protected note with one underlying asset. The performance of the underlying asset is determined by a predefined strategy – turn of the month. Turn of the month means that the note is exposed to the underlying asset only during a predefined number of days per month. | M7: This is a capital protected note with more than one underlying asset. The performance of the underlying asset is determined by calculating the difference in the return between two different underlying assets. | N7: This is a capital protected note with one underlying asset. The performance of the underlying asset is determined by a predefined strategy – turn of the month. Turn of the month means that the note is exposed to the underlying asset only during a predefined number of days per month. Each monthly performance is capped at a predefined level. If the sum of the monthly performances exceeds a predefined lock-in level, the minimum redemption price at maturity is increased to that level. | O7: This is a capital protected note with more than one underlying asset (currency pairs = basket short) in a basket. | P7: This is a capital protected note with more than one underlying currency pairs. At maturity the calculated returns for all the underlying baskets (currency pairs) is ranked. The best performer is then applied in order to calculate the return. | Q7: This is a capital protected note with more than one underlying asset in a basket. When calculating the basket performance, the performance of the underlying basket has a cap. | R7: This is a capital protected note linked to a reference rate. The note pays a floating interest rate, which has a floor and cap for each year. The interest rate is accumulated, meaning that the amount on which the interest is calculated is increasing with each interest rate period. On the redemption date, the note pays the nominal amount plus any accumulated interest rates. | S7: This is a capital protected note, linked to the relative difference between two underlying interest rates. The interest rate spread has a floor and a cap. On the redemption date, the note will pay the nominal amount + nominal amount x the relative difference (taking into account the floor and the cap) x participation ratio. | T7: This is a capital protected note with a fixed interest rate. The interest rate is accumulated, meaning that the amount on which the interest is calculated is increasing with each interest rate period. On the redemption date, the note pays the nominal amount plus accumulated interest rate. | U7: This is a capital protected note linked to a floating reference rate. The note pays a reference rate + interest margin, calculated on the nominal amount on each interest payment date. The annual interest rate has a cap. On the redemption date, the note pays the nominal amount. | V7: This is a capital protected note linked to a floating reference rate. If, on an interest determination date, the reference rate is within a predefined interval, the note will pay the reference rate plus the interest margin multiplied by the nominal amount on the next interest payment date. If the reference rate is lower than the floor, or higher than the cap, the note will pay the reference rate multiplied by the nominal amount on the next interest payment date. On the redemption date, the note pays the nominal amount. | W7: This is a capital protected note with one underlying asset. If, on a valuation date, the underlying asset is within a predefined interval, the note will be credited a predefined coupon. If, on a valuation date, the underlying asset is lower or higher than the predefined interval, no coupon will be credited for that period. The coupon is accumulated and paid on each interest payment date. On the redemption date, the note will pay nominal amount. | X7: This is a capital protected note linked to the relative difference between two underlying assets. The note will pay a fixed coupon for a set number of interest payment dates, calculated on the nominal amount. For the forthcoming interest payment dates, the note will pay a floating interest payment. On the redemption date, the note will pay the nominal amount. | Y7: This is a capital protected note, linked to the relative difference between two underlying interest rates. The interest rate spread has a floor and a cap. On the redemption date, the note will pay the nominal amount + nominal amount x the relative difference (taking into account the floor and the cap) x participation ratio. On each interest payment date, the note will pay a fixed interest, calculated on the nominal amount. | Z7: This is a capital protected note with one underlying asset. The note is affected by currency fluctuations. | AA7: This is a capital protected note with one underlying asset. The note pays a fixed guaranteed coupon, on each interest payment date, calculated on the nominal amount. The note is affected by currency fluctuations. | AB7: This is a capital protected note with one underlying asset. The note pays a fixed guaranteed coupon at maturity, calculated on the nominal amount. The note is affected by currency fluctuations. | AC7: This is a capital protected note with one underlying asset. The note pays a fixed guaranteed interest at maturity, calculated on the nominal amount. | AD7: This is a capital protected note with more than one underlying asset. The note pays a fixed guaranteed interest, on each interest payment date, calculated on the nominal amount. | AE7: This is a capital protected note with more than one underlying asset. The performance of the underlying assets is determined by a predefined strategy – turn of the month. Turn of the month means that the note is exposed to the underlying assets only during a predefined number of days per month. | AF7: This is a capital protected note with one underlying asset. Each monthly performance is capped at a predefined level. If the sum of the monthly performances exceeds a predefined lock-in level, the minimum redemption amount at maturity is increased to that level. | AG7: This is a capital protected note linked to the relative difference between two underlying assets. The note will pay a fixed coupon for a set number of interest payment dates, calculated on the nominal amount. For the forthcoming interest payment dates, the note will pay a floating coupon, linked to an interest rate spread. The interest rate spread has a floor and a cap. On the redemption date, the note will pay the nominal amount. | AH7: This is a capital protected note linked to the relative difference between two underlying assets. The note will pay a floating coupon, linked to an interest rate spread. The interest rate spread has a floor and a cap. On the redemption date, the note will pay the nominal amount. | AI7: This is a capital protected note with more than one underlying currency pairs. If the basket has a positive performance, the note will pay the nominal amount plus the nominal amount multiplied by the performance of the basket multiplied by the participation ratio, on the redemption date. When calculating the basket performance, each currency pair will be given a speicific weight in the basket. If the basket has an negative performance, the note will pay the nominal amount on the redemption date. | AJ7: This is a capital protected note with one underlying asset. The note pays a fixed guaranteed coupon, on each interest payment date, calculated on the nominal amount. | AK7: This is a capital protected note linked to a floating reference rate. The note pays a floating reference rate, calculated on the nominal amount, on each interest payment date. The annual interest rate has a cap and a floor. On the redemption date, the note pays the nominal amount. | AL7: This is a capital protected note linked to a reference rate. The note pays a floating interest rate (reference rate + interest margin), which has a cap for each year, calculated on the nominal amount. The interest rate is accumulated, meaning that the amount on which the interest is calculated is increasing with each interest rate period. On the redemption date, the note pays the nominal amount plus accumulated interest rates. | AM7: This is a capital protected note linked to a floating reference rate. The note pays a floating reference rate (reference rate + interest margin), calculated on the nominal amount, on each interest payment date. The annual interest rate has a cap and a floor. On the redemption date, the note pays the nominal amount. | AN7: This is a capital protected note linked to a floating reference rate. The note will pay a fixed interest for a set number of interest payment dates, calculated on the nominal amount. For the forthcoming interest payment dates, the note will pay a floating interest (reference rate + interest margin) calculcated on the nominal amount. The floating interest payments has a yearly cap. | AO7: This is a capital protected note with more than one underlying asset in a basket. When calculating the basket performance, a specified number of the best performing underlying assets in the basket will be given a fixed performance each. | AP7: This is a capital protected note linked to the relative difference between two underlying assets. The note will pay a fixed coupon on the first interest payment date, calculated on the nominal amount. For the forthcoming interest payment dates, the note will pay a floating coupon, linked to the performance of an interest rate spread.
A8: EUSIPA-code | B8: 1100 | C8: 1100 | D8: 1100 | E8: 1100 | F8: 1120 | G8: 1120 | H8: 1100 | I8: 1100 | J8: 1100 | K8: 1100 | L8: 1100 | M8: 1100 | N8: 1140 | O8: 1100 | P8: 1100 | Q8: 1120 | R8: 1120 | S8: 1120 | T8: 1100 | U8: 1120 | V8: 1120 | W8: 1120 | X8: 1100 | Y8: 1120 | Z8: 1100 | AA8: 1100 | AB8: 1100 | AC8: 1100 | AD8: 1100 | AE8: 1100 | AF8: 1140 | AG8: 1120 | AH8: 1120 | AI8: 1100 | AJ8: 1100 | AO8: 1100 | AP8: 1120
B9: 100%CapitalProtection | C9: 100%CapitalProtection | D9: 100%CapitalProtection | E9: 100%CapitalProtection | F9: 100%CapitalProtection | G9: 100%CapitalProtection | H9: 100%CapitalProtection | I9: 100%CapitalProtection | J9: 100%CapitalProtection | K9: 100%CapitalProtection | L9: 100%CapitalProtection | M9: 100%CapitalProtection | N9: 100%CapitalProtection | O9: 100%CapitalProtection | P9: 100%CapitalProtection | Q9: 100%CapitalProtection | R9: 100%CapitalProtection | S9: 100%CapitalProtection | T9: 100%CapitalProtection | U9: 100%CapitalProtection | V9: 100%CapitalProtection | W9: 100%CapitalProtection | X9: 100%CapitalProtection | Y9: 100%CapitalProtection | Z9: 100%CapitalProtection | AA9: 100%CapitalProtection | AB9: 100%CapitalProtection | AC9: 100%CapitalProtection | AD9: 100%CapitalProtection | AE9: 100%CapitalProtection | AF9: 100%CapitalProtection | AG9: 100%CapitalProtection | AH9: 100%CapitalProtection | AI9: 100%CapitalProtection | AJ9: 100%CapitalProtection | AK9: 100%CapitalProtection | AL9: 100%CapitalProtection | AM9: 100%CapitalProtection | AN9: 100%CapitalProtection | AO9: 100%CapitalProtection | AP9: 100%CapitalProtection
B10: Call1 | C10: Call1 | D10: Special | E10: Special | F10: Call1 | G10: DigitalObs | H10: Call1 | I10: Call1 | J10: Best-of Coupon/Participation | K10: Special | L10: Special | M10: UnderlyingSpreadPerformance | N10: Special | R10: FloatingFixings | U10: FloatingFixings | V10: FloatingFixings | X10: FloatingFixings | Y10: FinalFixings | AG10: FloatingFixing | AH10: FloatingFixing | AK10: FloatingFixing | AL10: FloatingFixing | AM10: FloatingFixing | AN10: FloatingFixing
D11: UnderlyingSwitchToFixed | E11: UnderlyingSwitchToFixed | F11: IndividualCaps | G11: AsianObservation | J11: UnderlyingSwitchToFixed | K11: TOM | L11: TOM | N11: TOM
D12: BestReplacement | E12: BestReplacement | J12: BestReplacement
A13: Type | B13: 1 b according to the MiFID (legal form?) | C13: 1 b according to the MiFID (legal form?) | D13: 1 b according to the MiFID (legal form?) | E13: 1 b according to the MiFID (legal form?) | F13: 1 b according to the MiFID (legal form?) | G13: 1 b according to the MiFID (legal form?) | H13: 1 b according to the MiFID (legal form?) | I13: 1 b according to the MiFID (legal form?) | J13: 1 b according to the MiFID (legal form?) | K13: 1 b according to the MiFID (legal form?) | L13: 1 b according to the MiFID (legal form?) | M13: 1 b according to the MiFID (legal form?) | N13: 1 b according to the MiFID (legal form?) | O13: 1 b according to the MiFID (legal form?) | P13: 1 b according to the MiFID (legal form?) | Q13: 1 b according to the MiFID (legal form?) | R13: 1 b according to the MiFID (legal form?) | S13: 1 b according to the MiFID (legal form?) | T13: 1 b according to the MiFID (legal form?) | U13: 1 b according to the MiFID (legal form?) | V13: 1 b according to the MiFID (legal form?) | W13: 1 b according to the MiFID (legal form?) | X13: 1 b according to the MiFID (legal form?) | Y13: 1 b according to the MiFID (legal form?) | Z13: 1 b according to the MiFID (legal form?) | AA13: 1 b according to the MiFID (legal form?) | AB13: 1 b according to the MiFID (legal form?) | AC13: 1 b according to the MiFID (legal form?) | AD13: 1 b according to the MiFID (legal form?) | AE13: 1 b according to the MiFID (legal form?) | AF13: 1 b according to the MiFID (legal form?) | AG13: 1 b according to the MiFID (legal form?) | AH13: 1 b according to the MiFID (legal form?) | AI13: 1 b according to the MiFID (legal form?) | AJ13: 1 b according to the MiFID (legal form?) | AK13: 1 b according to the MiFID (legal form?) | AL13: 1 b according to the MiFID (legal form?) | AM13: 1 b according to the MiFID (legal form?) | AN13: 1 b according to the MiFID (legal form?) | AO13: 1 b according to the MiFID (legal form?) | AP13: 1 b according to the MiFID (legal form?)
B14: Uncapped Capital Protection | C14: Uncapped Capital Protection | D14: Uncapped Capital Protection | E14: Uncapped Capital Protection | F14: Capped Capital Protected | G14: Capped Capital Protected | H14: Uncapped Capital Protection | I14: Uncapped Capital Protection | J14: Uncapped Capital Protection | K14: Uncapped Capital Protection | L14: Uncapped Capital Protection | M14: Uncapped Capital Protection | N14: Capital Protection with Coupon | O14: Uncapped Capital Protection | P14: Uncapped Capital Protection | Q14: Capped Capital Protection | R14: Capped Capital Protection | S14: Capped Capital Protection | T14: Capped Capital Protection | U14: Capped Capital Protection | V14: Capped Capital Protection | W14: Capped Capital Protection | X14: Capped Capital Protection | Y14: Capped Capital Protection | Z14: Capped Capital Protection | AA14: Capped Capital Protection | AB14: Capped Capital Protection | AC14: Capped Capital Protection | AD14: Capped Capital Protection | AE14: Capped Capital Protection | AF14: Capped Capital Protection | AG14: Capped Capital Protection | AH14: Capped Capital Protection | AI14: Capped Capital Protection | AJ14: Capped Capital Protection | AK14: Capped Capital Protection | AO14: Uncapped Capital Protection | AP14: Capped Capital Protection
B15: Underlying asset(s) (initial price) | C15: Underlying asset(s) (initial price) | D15: Underlying asset(s) (initial price) | E15: Underlying asset(s) (initial price) | F15: Underlying asset(s) (initial price) | G15: Underlying asset(s) (initial price) | H15: Underlying asset(s) (initial price) | I15: Underlying asset(s) (initial price) | J15: Underlying asset(s) (initial price) | K15: Underlying asset(s) (initial price) | L15: Underlying asset(s) (initial price) | M15: Underlying asset(s) (initial price) | N15: Underlying asset(s) (initial price) | O15: Underlying asset(s) (initial price) | P15: Underlying asset(s) (initial price) | Q15: Underlying asset(s) (initial price) | R15: Underlying asset(s) | S15: Underlying asset(s) (initial price) | T15: Underlying asset(s) (initial price) | U15: Underlying asset(s) (initial price) | V15: Underlying asset(s) (initial price) | W15: Underlying asset(s) (initial price) | X15: Underlying asset(s) (initial price) | Y15: Underlying asset(s) (initial price) | Z15: Underlying asset(s) (initial price) | AA15: Underlying asset(s) (initial price) | AB15: Underlying asset(s) (initial price) | AC15: Underlying asset(s) (initial price) | AD15: Underlying asset(s) (initial price) | AE15: Underlying asset(s) (initial price) | AF15: Underlying asset(s) (initial price) | AG15: Underlying asset(s) (initial price) | AH15: Underlying asset(s) (initial price) | AI15: Underlying asset(s) (initial price) | AJ15: Underlying asset(s) (initial price) | AL15: Underlying asset(s) (initial price) | AM15: Underlying asset(s) (initial price) | AN15: Underlying asset(s) (initial price) | AO15: Underlying asset(s) (initial price) | AP15: Underlying asset(s) (initial price)
A16: How the investment works | B16: The objective is to benefit from a rising market, and at the same time have the protection of getting back the nominal amount if the market is falling. | C16: The objective is to benefit from a rising market, and at the same time have the protection of getting back the nominal amount if the market is falling. | D16: The objective is to benefit from a rising market, and at the same time have the protection of getting back the nominal amount if the market is falling. | E16: The objective is to benefit from a rising market, and at the same time have the protection of getting back the nominal amount if the market is falling. | F16: The objective is to benefit from a rising market, and at the same time have the protection of getting back the nominal amount if the market is falling. | G16: The objective is to benefit from a rising market, and at the same time have the protection of getting back the nominal amount if the market is falling. | H16: The objective is to benefit from a rising market, and at the same time have the protection of getting back the nominal amount if the market is falling. | I16: The objective is to benefit from a rising market, and at the same time have the protection of getting back the nominal amount if the market is falling. | J16: The objective is to benefit from a rising market, and at the same time have the protection of getting back the nominal amount if the market is falling. | K16: The objective is to benefit from a rising market, and at the same time have the protection of getting back the nominal amount if the market is falling. | L16: The objective is to benefit from a rising market, and at the same time have the protection of getting back the nominal amount if the market is falling. | M16: The objective is to benefit from the relative difference between two underlying assets, and at the same time have the protection of getting back the nominal amount if the market is falling. | N16: The objective is to benefit from a rising market, and at the same time have the protection of getting back the nominal amount if the market is falling. | O16: The objective is to benefit from a rising market, and at the same time have the protection of getting back the nominal amount if the market is falling. | P16: The objective is to benefit from a rising market, and at the same time have the protection of getting back the nominal amount if the market is falling. | Q16: The objective is to benefit from a rising market, and at the same time have the protection of getting back the nominal amount if the market is falling. | R16: The objective is to benefit from a positive interest rate market, and at the same time have the protection of getting back the nominal amount if the market is falling. | S16: The objective is to benefit from the relative difference between two underlying assets, and at the same time have the protection of getting back the nominal amount if the market is falling. | T16: The objective is to receive the predefined interest payments, and at the same time have the protection of getting back the nominal amount if the market is falling. | U16: The objective is to benefit from a positive interest rate market, and at the same time have the protection of getting back the nominal amount if the market is falling. | V16: The objective is to benefit from a positive interest rate market, and at the same time have the protection of getting back the nominal amount if the market is falling. | W16: The objective is to benefit from a rising market, and at the same time have the protection of getting back the nominal amount if the market is falling. | X16: The objective is to benefit from the relative difference between two underlying assets, and at the same time have the protection of getting back the nominal amount if the market is falling. | Y16: The objective is to benefit from the relative difference between two underlying assets, and at the same time have the protection of getting back the nominal amount if the market is falling. | Z16: The objective is to benefit from a rising market, and at the same time have the protection of getting back the nominal amount if the market is falling. | AA16: The objective is to benefit from a rising market, and at the same time have the protection of getting back the nominal amount if the market is falling. | AB16: The objective is to benefit from a rising market, and at the same time have the protection of getting back the nominal amount if the market is falling. | AC16: The objective is to benefit from a rising market, and at the same time have the protection of getting back the nominal amount if the market is falling. | AD16: The objective is to benefit from a rising market, and at the same time have the protection of getting back the nominal amount if the market is falling. | AE16: The objective is to benefit from a rising market, and at the same time have the protection of getting back the nominal amount if the market is falling. | AF16: The objective is to benefit from a rising market, and at the same time have the protection of getting back the nominal amount if the market is falling. | AG16: The objective is to benefit from the relative difference between two underlying assets, and at the same time have the protection of getting back the nominal amount if the market is falling. | AH16: The objective is to benefit from the relative difference between two underlying assets, and at the same time have the protection of getting back the nominal amount if the market is falling. | AI16: The objective is to benefit from a rising market, and at the same time have the protection of getting back the nominal amount if the market is falling. | AJ16: The objective is to benefit from a rising market, and at the same time have the protection of getting back the nominal amount if the market is falling. | AK16: The objective is to benefit from a positive interest rate market, and at the same time have the protection of getting back the nominal amount if the market is falling. | AL16: The objective is to benefit from a positive interest rate market, and at the same time have the protection of getting back the nominal amount if the market is falling. | AM16: The objective is to benefit from a positive interest rate market, and at the same time have the protection of getting back the nominal amount if the market is falling. | AN16: The objective is to benefit from a positive interest rate market, and at the same time have the protection of getting back the nominal amount if the market is falling. | AO16: The objective is to benefit from a rising market, and at the same time have the protection of getting back the nominal amount if the market is falling. | AP16: The objective is to benefit from the relative difference between two underlying assets, and at the same time have the protection of getting back the nominal amount if the market is falling.
B17: The return of the investment depends on the performance of a basket of underlying assets during the lifetime of the investment. | C17: The return of the investment depends on the performance of a basket of underlying assets during the lifetime of the investment. | D17: The return of the investment depends on the performance of a basket of underlying assets during the lifetime of the investment. | E17: The return of the investment depends on the performance of a basket of underlying assets during the lifetime of the investment. | F17: The return of the investment depends on the performance of a basket of underlying assets during the lifetime of the investment. | G17: The return of the investment depends on the performance of a basket of underlying assets during the lifetime of the investment. | H17: The return of the investment depends on the performance of an underlying asset during the lifetime of the investment. | I17: The return of the investment depends on the performance of several baskets of underlying assets during the lifetime of the investment. | J17: The return of the investment depends on the performance of a basket of underlying assets during the lifetime of the investment. | K17: The return of the investment depends on the performance of an underlying asset during the lifetime of the investment. | L17: The return of the investment depends on the performance of an underlying asset during the lifetime of the investment. | M17: The return of the investment depends on the relative performance of the underlying assets during the lifetime of the investment. | N17: The return of the investment depends on the performance of the underlying asset during the lifetime of the investment. | O17: The return of the investment depends on the performance of a basket of underlying assets during the lifetime of the investment. | P17: The return of the investment depends on the performance of a basket of underlying currency pairs during the lifetime of the investment. | Q17: The return of the investment depends on the performance of a basket of underlying assets during the lifetime of the investment. | R17: The return of the investment is linked to a floating interest rate. | S17: The return of the investment depends on the relative difference between two underlying interest rates. | T17: The return of the investment is linked to a fixed interest rate. | U17: The return of the investment is linked to a floating reference rate. | V17: The return of the investment is linked to a floating reference rate. | W17: The return of the investment depends on the performance of an underlying asset during the lifetime of the investment. | X17: The return of the investment depends on the relative difference between two underlying assets during the lifetime of the investment. | Y17: The return of the investment depends on the relative difference (taking into account the performance floor and the performance cap) between two underlying assets during the lifetime of the investment. | Z17: The return of the investment depends on the performance of an underlying asset during the lifetime of the investment. | AA17: The return of the investment depends on the performance of an underlying asset during the lifetime of the investment. | AB17: The return of the investment depends on the performance of an underlying asset during the lifetime of the investment. | AC17: The return of the investment depends on the performance of an underlying asset during the lifetime of the investment. | AD17: The return of the investment depends on the performance of a basket of underlying assets during the lifetime of the investment. | AE17: The return of the investment depends on the performance of a basket of underlying assets during the lifetime of the investment. | AF17: The return of the investment depends on the performance of an underlying asset during the lifetime of the investment. | AG17: The return of the investment depends on the relative difference between two underlying assets (taking into account the performance floor and the performance cap) during the lifetime of the investment. | AH17: The return of the investment depends on the relative difference between two underlying assets (taking into account the performance floor and the performance cap) during the lifetime of the investment. | AI17: The return of the investment depends on the performance of a basket of currency pairs during the lifetime of the investment. | AJ17: The return of the investment depends on the performance of an underlying asset during the lifetime of the investment. | AK17: The return of the investment is linked to a floating interest rate. | AL17: The return of the investment is linked to a floating interest rate. | AM17: The return of the investment is linked to a floating interest rate. | AN17: The return of the investment is linked to one fixed and one floating interest rate. | AO17: The return of the investment depends on the performance of a basket of underlying assets during the lifetime of the investment. | AP17: The return of the investment depends on the relative difference between two underlying assets (taking into account the performance floor and the performance cap) during the lifetime of the investment.
B18: If the basket has a positive performance, the note will pay the nominal amount plus the nominal amount multiplied by the performance of the basket multiplied by the participation ratio, on the redemption date. Currency fluctuations will also affect the return of the investment. | C18: If the basket has a positive performance, the note will pay the nominal amount plus the nominal amount multiplied by the performance of the basket multiplied by the participation ratio, on the redemption date. | D18: If the basket has a positive performance, the note will pay the nominal amount plus the nominal amount multiplied by the performance of the basket multiplied by the participation ratio, on the redemption date. When calculating the performance of the basket, a specified number of the best performing underlying assets in the basket will be assigned a fixed performance each (see specified numbers below). Currency fluctuations will also affect the return of the investment. | E18: If the basket has a positive performance, the note will pay the nominal amount plus the nominal amount multiplied by the performance of the basket multiplied by the participation ratio, on the redemption date. When calculating the performance of the basket, a specified number of the best performing underlying assets in the basket will be assigned a fixed performance each (see specified numbers below). | F18: If the basket has a positive performance, the note will pay the nominal amount plus the nominal amount multiplied by the performance of the basket multiplied by the participation ratio, on the redemption date. When calculating the performance of the basket, each underlying asset has a performance cap. | G18: If, on an interest determination date, the value of the basket is at or above it´s initial value, the note will pay a coupon that is equal to the lowest of the baskets performance and the coupon, on the next interest payment date. | H18: If the underlying asset has a positive performance, the note will pay the nominal amount plus the nominal amount multiplied by the performance of the underlying asset multiplied by the participation ratio, on the redemption date. | I18: If the best performing basket has a positive performance, the note will pay the nominal amount plus the nominal amount multiplied by the performance of that basket multiplied by the participation ratio, on the redemption date. | J18: When calculating the basket performance, a specified number of the best performing underlying assets in the basket will be assigned a fixed performance each (see specified numbers below). | K18: If the underlying asset has a positive performance, the note will pay the nominal amount plus the nominal amount multiplied by the performance of the underlying asset multiplied by the participation ratio, on the redemption date. | L18: If the underlying asset has a positive performance, the note will pay the nominal amount plus the nominal amount multiplied by the performance of the underlying asset multiplied by the participation ratio, on the redemption date. | M18: The relative performance of the underlying assets is determined by calculating the difference in the return between two underlying assets. | N18: The performance of the underlying asset is determined by a predefined strategy – turn of the month. Turn of the month means that the note is exposed to the underlying asset only during a predefined number of days per month. Each monthly performance is capped at a predefined level. There is also a lock-in feature, which means that if the sum of the monthly performances reaches a lock-in level the note will at least pay that amount on the redemption date. | O18: If the basket has a positive performance, the note will pay the nominal amount plus the nominal amount multiplied by the performance of the basket multiplied by the participation ratio, on the redemption date. | P18: If the best performing underlying currency pair has a positive performance, the note will pay the nominal amount plus the nominal amount multiplied by the performance of that currency pair multiplied by the participation ratio, on the redemption date. | Q18: If the basket has a positive performance, the note will pay the nominal amount plus the nominal amount multiplied by the performance of the basket multiplied by the participation ratio, on the redemption date. When calculating the performance, the performance has a cap. | R18: The performance of the note is linked to a reference rate. The interest rate has a yearly performance floor and cap. On each interest payment date, the interest is accumulated and the forthcoming interest rates will be calculated on the sum of the nominal amount plus the accumulated interest rates. | S18: If the relative difference between the underlying interest rates is within a predefined interval, the note will pay the nominal amount plus the nominal amount multiplied by the participation ratio multiplied by the relative difference between the underlying assets minus the performance floor, on the redemption date. | T18: For each interest determination period, a fixed interest will be credited. The interest is accumulated, and the forthcoming interest will be calculated on the sum of the nominal amount and the accumulated interest rates. | U18: The note will pay a floating interest rate (reference rate plus interest margin), calculated on the nominal amount, on each interest payment date. The floating interest rate has a yearly performance cap. | V18: If, on an interest determination date, the reference rate is within a predefined interval, the note will pay the reference rate plus the interest margin multiplied by the nominal amount on the next interest payment date. | W18: If, on a valuation date, the underlying asset is at or above the yearly performance floor and at or below the yearly performance cap, the note will be credited the coupon multiplied by the nominal amount. The credited coupons will be paid on the next interest payment date. | X18: The note will pay a fixed interest, calculated on the nominal amount, for a set number of interest payment dates. For the forthcoming interest payment dates, the note will pay a floating interest. | Y18: The note will pay a fixed interest, calculated on the nominal amount, on each interest payment date. | Z18: If the underlying asset has a positive performance, the note will pay the nominal amount plus the nominal amount multiplied by the performance of the underlying asset multiplied by the participation ratio, on the redemption date. Currency fluctuations will also affect the return of the investment. | AA18: The note will pay a fixed interest, calculated on the nominal amount, on each interest payment date. | AB18: The note will pay a coupon, calculated on the nominal amount, on the redemption date. | AC18: The note will pay a coupon, calculated on the nominal amount, on the redemption date. | AD18: The note will pay a fixed interest, calculated on the nominal amount, on each interest payment date. | AE18: If the basket has a positive performance, the note will pay the nominal amount plus the nominal amount multiplied by the performance of the basket multiplied by the participation ratio, on the redemption date. | AF18: The monthly performance has a predefined performance cap. There is also a lock-in feature, which means that if the sum of the monthly performances reaches a lock-in level the note will at least pay that amount on the redemption date. | AG18: The note will pay a fixed interest, calculated on the nominal amount, for a set number of interest payment dates. For the forthcoming interest payment dates, the note will pay a floating interest. | AH18: If, on an interest determination date, the relative difference between the underlying interest rates is within a predefined interval, the note will pay the nominal amount multiplied by the participation ratio multiplied by the relative difference between the underlying assets on the next interest payment date. | AI18: If the basket has a positive performance, the note will pay the nominal amount plus the nominal amount multiplied by the performance of the basket multiplied by the participation ratio, on the redemption date. When calculating the basket performance, each currency pair will be given a speicific weight in the basket. | AJ18: The note will pay a fixed interest, calculated on the nominal amount, on each interest payment date. | AK18: The note will pay a floating interest (the reference rate), calculated on the nominal amount, on each interest payment date. The interest rate has a yearly performance floor and performance cap. | AL18: The performance of the note is linked to an interest rate (reference rate plus interest margin). The interest rate has a yearly performance cap. On each interest payment date, the interest is accumulated and the forthcoming interest rates will be calculated on the sum of the nominal amount plus the accumulated interest rates. | AM18: The note will pay a floating interest (reference rate plus interest margin), calculated on the nominal amount, on each interest payment date. The interest rate has a yearly performance floor and performance cap. | AN18: The note will pay a fixed interest, calculated on the nominal amount, for a set number of interest payment dates. For the forthcoming interest payment dates, the note will pay a floating interest (reference rate plus interest margin), calculated on the nominal amount. The floating interest payments has a yearly performance cap. | AO18: If the basket has a positive performance, the note will pay the nominal amount plus the nominal amount multiplied by the performance of the basket multiplied by the participation ratio, on the redemption date. When calculating the performance of the basket, a specified number of the best performing underlying assets in the basket will be assigned a fixed performance each (see specified numbers below). | AP18: The note will pay a fixed interest, calculated on the nominal amount, on the fixed interest payment date.
B19: If the basket has an negative performance, the note will pay the nominal amount on the redemption date. | C19: If the basket has an negative performance, the note will pay the nominal amount on the redemption date. | D19: If the basket has an negative performance, the note will pay the nominal amount on the redemption date. | E19: If the basket has an negative performance, the note will pay the nominal amount on the redemption date. | F19: If the basket has an negative performance, the note will pay the nominal amount on the redemption date. | G19: If, on an interest determination date, the value of the basket is below it´s initial value no coupon will be paid on the next interest payment day. | H19: If the underlying asset has an negative performance, the note will pay the nominal amount on the redemption date. | I19: If the best performing basket has an negative performance, the note will pay the nominal amount on the redemption date. | J19: If the basket performance is within a predefined interval, the note will pay the nominal amount plus the nominal amount multiplied by the coupon, on the redemption date. | K19: The performance of the underlying asset is determined by a predefined strategy – turn of the month. Turn of the month means that the note is exposed to the underlying asset only during a predefined number of days per month. Currency fluctuations will also affect the return of the investment. | L19: The performance of the underlying asset is determined by a predefined strategy – turn of the month. Turn of the month means that the note is exposed to the underlying asset only during a predefined number of days per month. | M19: If the relative performance is positive, the note will pay the nominal amount plus the nominal amount multiplied by the relative performance multiplied by the participation ratio, on the redemption date. | N19: If the underlying asset has a positive performance, the note will pay the the nominal amount plus the higher of the highest lock-in level that has been reached, and the actual performance of the basket, on the redemption date. | O19: If the basket has an negative performance, the note will pay the nominal amount on the redemption date. | P19: If the best performing underlying currency pair has an negative performance, the note will pay the nominal amount on the redemption date. | Q19: If the basket has an negative performance, the note will pay the nominal amount on the redemption date. | R19: On the redemption date, the note will pay the nominal amount plus the accumulated interest rate. | S19: If the relative difference between the underlying interest rates is higher than the predefined interval, the note will pay the nominal amount plus the nominal amount multiplied by the participation ratio multiplied by the sum of the performance cap minus the performance floor, on the redemption date. | T19: The note will pay the nominal amount and the accumulated interest rate, on the redemption date., | U19: The note will pay the nominal amount on the redemption date. | V19: If, on an interest determination date, the reference rate is lower than the performance floor, or higher than the performance cap, the note will pay the reference rate multiplied by the nominal amount on the next interest payment date. | W19: If, on a valuation date, the underlying asset is lower than the yearly performance floor or higher than the yearly performance cap, no coupon will be credited for that period. | X19: The note will pay the nominal amount on the redemption date. | Y19: If, on the valuation date, the relative difference between the underlying interest rates is within a predefined interval, the note will pay the nominal amount multiplied by the participation ratio multiplied by the relative difference between the underlying assets. | Z19: If the underlying asset has an negative performance, the note will pay the nominal amount on the redemption date. | AA19: If the underlying asset has a positive performance, the note will pay the nominal amount plus the nominal amount multiplied by the performance of the underlying asset multiplied by the participation ratio, on the redemption date. Currency fluctuations will also affect the return of the investment. | AB19: If the underlying asset has a positive performance, the note will pay the nominal amount plus the nominal amount multiplied by the performance of the underlying asset multiplied by the participation ratio, on the redemption date. Currency fluctuations will also affect the return of the investment. | AC19: If the underlying asset has a positive performance, the note will pay the nominal amount plus the nominal amount multiplied by the performance of the underlying asset multiplied by the participation ratio, on the redemption date. | AD19: If the basket has a positive performance, the note will pay the nominal amount plus the nominal amount multiplied by the performance of the basket multiplied by the participation ratio, on the redemption date. | AE19: The performance of the basket is determined by a predefined strategy – turn of the month. Turn of the month means that the note is exposed to the basket only during a predefined number of days per month. | AF19: If the underlying asset has a positive performance, the note will pay the nominal amount plus the higher of the highest lock-in level that has been reached, and the actual performance of the underlying asset, on the redemption date. | AG19: If, on an interest determination date, the relative difference between the underlying interest rates is within a predefined interval, the note will pay the nominal amount multiplied by the participation ratio multiplied by the relative difference between the underlying assets on the next floating interest payment date. | AH19: If, on an interest determination date, the relative difference between the underlying interest rates is higher than a predefined interval, the note will pay the maximum coupon on the next interest payment date. | AI19: If the basket has an negative performance, the note will pay the nominal amount on the redemption date. | AJ19: If the underlying asset has a positive performance, the note will pay the nominal amount plus the nominal amount multiplied by the performance of the underlying asset multiplied by the participation ratio, on the redemption date. | AK19: The note will pay the nominal amount on the redemption date. | AL19: The note will pay the nominal amount plus the accumulated interest rate on the redemption date. | AM19: The note will pay the nominal amount on the redemption date. | AN19: The note will pay the nominal amount on the redemption date. | AO19: If the basket has an negative performance, the note will pay the nominal amount on the redemption date. | AP19: If, on an interest determination date, the relative difference between the underlying interest rates is above the predefined barrier, the note will pay the nominal amount multiplied by the fixed interest multiplied by the number of valuation dates where the relative difference is above the the barrier divided by 12, on the next the participation ratio multiplied by the relative difference between the underlying assets on the next floating interest payment date.
G20: The note will pay the nominal amount on the redemption date. | J20: If the basket performance is higher than the predefined interval, the note will pay the nominal amount plus the nominal amount multiplied by the performance of the basket multiplied by the participation ratio, on the redemption date. | K20: If the underlying asset has an negative performance, the note will pay the nominal amount on the redemption date. | L20: If the underlying asset has an negative performance, the note will pay the nominal amount on the redemption date. | M20: If the relative performance is negative the note will pay the nominal amount on the redemption date. | N20: If the underlying asset has a negative performance, the note will pay the higher of the nominal amount plus the highest lock-in level that has been reached, and the nominal amount, on the redemption date. | S20: If, on the valuation date, the relative difference is lower than the predefined interval, the note will pay the nominal amount on the redemption date. | V20: The note will pay the nominal amount on the redemption date. | W20: The note will pay the nominal amount on the redemption date. | Y20: If, on the valuation date, the relative difference between the underlying interest rates is higher than a predefined interval, the note will pay the maximum coupon on the next floating copuon payment date. | AA20: If the underlying asset has an negative performance, the note will pay the nominal amount on the redemption date. | AB20: If the underlying asset has an negative performance, the note will pay the nominal amount on the redemption date. | AC20: If the underlying asset has an negative performance, the note will pay the nominal amount on the redemption date. | AD20: If the basket has an negative performance, the note will pay the nominal amount on the redemption date. | AE20: If the basket has an negative performance, the note will pay the nominal amount on the redemption date. | AF20: If the underlying asset has a negative performance, the note will pay the higher of the nominal amount and the nominal amount plus the highest lock-in level that has been reached, on the redemption date. | AG20: If, on an interest determination date, the relative difference between the underlying interest rates is higher than a predefined interval, the note will pay the maximum coupon on the next floating interest payment date. | AH20: If, on an interest determination date, the relative difference between the underlying interest rates is lower than a predefined interval, no interest will be paid on the next interest payment date. | AJ20: If the underlying asset has an negative performance, the note will pay the nominal amount on the redemption date. | AP20: The note will pay the nominal amount on the redemption date.
J21: If the basket has an negative performance, the note will pay the nominal amount on the redemption date. | Y21: If, on the valuation date, the relative difference is lower than the predefined interval, the note will pay the nominal amount on the redemption date. | AG21: If, on an interest determination date, the relative difference between the underlying interest rates is lower than a predefined interval, no floating interest will be paid on the next floating interest payment date. | AH21: The note will pay the nominal amount on the redemption date.
A22: Key figures: | AG22: The note will pay the nominal amount on the redemption date.
B24: Minimum subscription amount | C24: Minimum subscription amount | D24: Minimum subscription amount | E24: Minimum subscription amount | F24: Minimum subscription amount | G24: Minimum subscription amount | H24: Minimum subscription amount | I24: Minimum subscription amount | J24: Minimum subscription amount | K24: Minimum subscription amount | L24: Minimum subscription amount | M24: Minimum subscription amount | N24: Minimum subscription amount | O24: Minimum subscription amount | P24: Minimum subscription amount | Q24: Minimum subscription amount | R24: Minimum subscription amount | S24: Minimum subscription amount | T24: Minimum subscription amount | U24: Minimum subscription amount | V24: Minimum subscription amount | W24: Minimum subscription amount | X24: Minimum subscription amount | Y24: Minimum subscription amount | Z24: Minimum subscription amount | AA24: Minimum subscription amount | AB24: Minimum subscription amount | AC24: Minimum subscription amount | AD24: Minimum subscription amount | AE24: Minimum subscription amount | AF24: Minimum subscription amount | AG24: Minimum subscription amount | AH24: Minimum subscription amount | AI24: Minimum subscription amount | AJ24: Minimum subscription amount | AK24: Minimum subscription amount | AL24: Minimum subscription amount | AM24: Minimum subscription amount | AN24: Minimum subscription amount | AO24: Minimum subscription amount | AP24: Minimum subscription amount
B25: Subscription end date | C25: Subscription end date | D25: Subscription end date | E25: Subscription end date | F25: Subscription end date | G25: Subscription end date | H25: Subscription end date | I25: Subscription end date | J25: Subscription end date | K25: Subscription end date | L25: Subscription end date | M25: Subscription end date | N25: Subscription end date | O25: Subscription end date | P25: Subscription end date | Q25: Subscription end date | R25: Subscription end date | S25: Subscription end date | T25: Subscription end date | U25: Subscription end date | V25: Subscription end date | W25: Subscription end date | X25: Subscription end date | Y25: Subscription end date | Z25: Subscription end date | AA25: Subscription end date | AB25: Subscription end date | AC25: Subscription end date | AD25: Subscription end date | AE25: Subscription end date | AF25: Subscription end date | AG25: Subscription end date | AH25: Subscription end date | AI25: Subscription end date | AJ25: Subscription end date | AK25: Subscription end date | AL25: Subscription end date | AM25: Subscription end date | AN25: Subscription end date | AO25: Subscription end date | AP25: Subscription end date
B26: Issue price | C26: Issue price | D26: Issue price | E26: Issue price | F26: Issue price | G26: Issue price | H26: Issue price | I26: Issue price | J26: Issue price | K26: Issue price | L26: Issue price | M26: Issue price | N26: Issue price | O26: Issue price | P26: Issue price | Q26: Issue price | R26: Issue price | S26: Issue price | T26: Issue price | U26: Issue price | V26: Issue price | W26: Issue price | X26: Issue price | Y26: Issue price | Z26: Issue price | AA26: Issue price | AB26: Issue price | AC26: Issue price | AD26: Issue price | AE26: Issue price | AF26: Issue price | AG26: Issue price | AH26: Issue price | AI26: Issue price | AJ26: Issue price | AK26: Issue price | AL26: Issue price | AM26: Issue price | AN26: Issue price | AO26: Issue price | AP26: Issue price
B27: Issue date | C27: Issue date | D27: Issue date | E27: Issue date | F27: Issue date | G27: Issue date | H27: Issue date | I27: Issue date | J27: Issue date | K27: Issue date | L27: Issue date | M27: Issue date | N27: Issue date | O27: Issue date | P27: Issue date | Q27: Issue date | R27: Issue date | S27: Issue date | T27: Issue date | U27: Issue date | V27: Issue date | W27: Issue date | X27: Issue date | Y27: Issue date | Z27: Issue date | AA27: Issue date | AB27: Issue date | AC27: Issue date | AD27: Issue date | AE27: Issue date | AF27: Issue date | AG27: Issue date | AH27: Issue date | AI27: Issue date | AJ27: Issue date | AK27: Issue date | AL27: Issue date | AM27: Issue date | AN27: Issue date | AO27: Issue date | AP27: Issue date
B28: Nominal amount/Capital protection + currency | C28: Nominal amount/Capital protection + currency | D28: Nominal amount/Capital protection + currency | E28: Nominal amount/Capital protection + currency | F28: Nominal amount/Capital protection + currency | G28: Nominal amount/Capital protection + currency | H28: Nominal amount/Capital protection + currency | I28: Nominal amount/Capital protection + currency | J28: Nominal amount/Capital protection + currency | K28: Nominal amount/Capital protection + currency | L28: Nominal amount/Capital protection + currency | M28: Nominal amount/Capital protection + currency | N28: Nominal amount/Capital protection + currency | O28: Nominal amount/Capital protection + currency | P28: Nominal amount/Capital protection + currency | Q28: Nominal amount/Capital protection + currency | R28: Nominal amount/Capital protection + currency | S28: Nominal amount/Capital protection + currency | T28: Nominal amount/Capital protection + currency | U28: Nominal amount/Capital protection + currency | V28: Nominal amount/Capital protection + currency | W28: Nominal amount/Capital protection + currency | X28: Nominal amount/Capital protection + currency | Y28: Nominal amount/Capital protection + currency | Z28: Nominal amount/Capital protection + currency | AA28: Nominal amount/Capital protection + currency | AB28: Nominal amount/Capital protection + currency | AC28: Nominal amount/Capital protection + currency | AD28: Nominal amount/Capital protection + currency | AE28: Nominal amount/Capital protection + currency | AF28: Nominal amount/Capital protection + currency | AG28: Nominal amount/Capital protection + currency | AH28: Nominal amount/Capital protection + currency | AI28: Nominal amount/Capital protection + currency | AJ28: Nominal amount/Capital protection + currency | AK28: Nominal amount/Capital protection + currency | AL28: Nominal amount/Capital protection + currency | AM28: Nominal amount/Capital protection + currency | AN28: Nominal amount/Capital protection + currency | AO28: Nominal amount/Capital protection + currency | AP28: Nominal amount/Capital protection + currency
B29: Participation ratio | C29: Participation ratio | D29: Participation ratio | E29: Participation ratio | F29: Participation ratio | G29: Coupon | H29: Participation ratio | I29: Participation ratio | J29: Participation ratio | K29: Participation ratio | L29: Participation ratio | M29: Participation ratio | N29: Performance cap | O29: Participation ratio | P29: Participation ratio | Q29: Participation ratio | R29: Reference rate | S29: Participation ratio | T29: Fixed interest per annum | U29: Interest margin per annum | V29: Reference rate | W29: Coupon per annum | X29: Fixed interest per annum | Y29: Participation ratio | Z29: Participation ratio | AA29: Fixed interest per annum | AB29: Coupon | AC29: Coupon | AD29: Fixed interest per annum | AE29: Participation ratio | AF29: Performance cap | AG29: Fixed interest rate per annum | AH29: Participation ratio | AI29: Participation ratio | AJ29: Fixed interest per annum | AK29: Reference rate | AL29: Interest margin per annum | AM29: Interest margin per annum | AN29: Fixed interest per annum | AO29: Participation ratio | AP29: Fixed interest rate per annum
B30: Currency exposure | C30: Redemption date | D30: Number of fixed underlying assets | E30: Number of fixed underlying assets | F30: Performance cap | G30: Interest determination date(s) | H30: Redemption date | I30: Redemption date | J30: Coupon | K30: Currency exposure | L30: Redemption date | M30: Redemption date | N30: Lock-in level(s) | O30: Redemption date | P30: Redemption date | Q30: Performance cap | R30: Performance floor | S30: Performance floor | T30: Interest determination period(s) | U30: Reference rate | V30: Interest margin per annum | W30: Performance floor per annum | X30: Fixed interest payment date(s) | Y30: Maximum coupon | Z30: Currency exposure | AA30: Participation ratio | AB30: Participation ratio | AC30: Participation ratio | AD30: Participation ratio | AE30: Redemption date | AF30: Lock-in level(s) | AG30: Performance floor | AH30: Performance floor | AI30: Redemption date | AJ30: Participation ratio | AK30: Performance floor | AL30: Reference rate | AM30: Reference rate | AN30: Reference rate | AO30: Number of fixed underlying assets | AP30: Performance floor
B31: Redemption date | D31: Fixed performance for best performing underlying assets | E31: Fixed performance for best performing underlying assets | F31: Redemption date | G31: Interest payment date(s) | J31: Number of fixed underlying assets | K31: Redemption date | N31: Redemption date | Q31: Redemption date | R31: Performance cap | S31: Performance cap | T31: Redemption date | U31: Performance cap | V31: Performance floor | W31: Performance cap per annum | X31: Floating interest payment date(s) | Y31: Performance cap | Z31: Redemption date | AA31: Currency exposure | AB31: Currency exposure | AC31: Redemption date | AD31: Interest payment date(s) | AF31: Redemption date | AG31: Performance cap | AH31: Performance cap | AJ31: Interest payment date(s) | AK31: Performance cap | AL31: Performance cap | AM31: Performance floor | AN31: Interest margin per annum | AO31: Fixed performance for best performing underlying assets | AP31: Performance cap
D32: Currency exposure | E32: Redemption date | G32: Redemption date | H32: Initial valuation date | I32: Initial valuation date | J32: Fixed performance for best performing underlying assets | R32: Interest payment date(s) | S32: Redemption date | U32: Interest payment date(s) | V32: Performance cap | W32: Valuation date(s) | X32: Redemption date | Y32: Performance floor | AA32: Interest payment date(s) | AB32: Redemption date | AD32: Redemption date | AG32: Maximum coupon | AH32: Maximum coupon | AJ32: Redemption date | AK32: Interest payment date(s) | AL32: Interest payment date(s) | AM32: Performance cap | AN32: Performance cap | AO32: Redemption date | AP32: Fixed interest payment date(s)
C33: Initial valuation date | D33: Redemption date | F33: Initial valuation date | H33: Valuation date(s) | I33: Valuation date(s) | J33: Redemption date | K33: Initial valuation date | L33: Initial valuation date | M33: Initial valuation date | N33: Initial valuation date | O33: Initial valuation date | P33: Initial valuation date | Q33: Initial valuation date | R33: Redemption date | T33: Initial valuation date | U33: Redemption date | V33: Interest determination date(s) | W33: Interest payment date(s) | Y33: Interest payment date(s) | AA33: Redemption date | AG33: Participation ratio | AH33: Interest determination date(s) | AK33: Redemption date | AL33: Redemption date | AM33: Interest payment date(s) | AN33: Fixed interest payment date(s) | AP33: Floating interest payment date(s)
C34: Valuation date(s) | E34: Initial valuation date | F34: Valuation date(s) | G34: Initial valuation date | K34: Valuation date(s) | L34: Valuation date(s) | M34: Valuation date(s) | N34: Valuation date(s) | O34: Valuation date(s) | P34: Valuation date(s) | Q34: Valuation date(s) | S34: Initial valuation date | V34: Interest payment date(s) | W34: Redemption date | X34: Valuation date(s) | Y34: Valuation date(s) | Z34: Valuation date(s) | AC34: Initial valuation date | AD34: Initial valuation date | AE34: Initial valuation date | AF34: Initial valuation date | AG34: Fixed interest payment date(s) | AH34: Interest payment date(s) | AM34: Redemption date | AN34: Floating interest payment date(s) | AO34: Initial valuation date | AP34: Interest determination date(s)
B35: Initial valuation date | D35: Initial valuation date | E35: Valuation date(s) | G35: Valuation date(s) | J35: Initial valuation date | K35: FX valuation start date | R35: Interest determination date(s) | S35: Valuation date(s) | U35: Initial valuation date | V35: Redemption date | Y35: Redemption date | Z35: FX valuation start date | AB35: Initial valuation date | AC35: Valuation date(s) | AD35: Valuation date(s) | AE35: Valuation date(s) | AF35: Valuation date(s) | AG35: Floating interest payment date(s) | AH35: Redemption date | AN35: Redemption date | AO35: Valuation date(s) | AP35: Valuation date(s)
B36: Valuation date(s) | D36: Valuation date(s) | J36: Valuation date(s) | K36: FX valuation end date | U36: Interest determination date(s) | W36: Initial valuation date | Z36: FX valuation end date | AA36: Initial valuation date | AB36: Valuation date(s) | AG36: Interest determination date(s) | AI36: Initial valuation date | AP36: Redemption date
B37: FX valuation start date | D37: FX valuation start date | U37: Valuation date(s) | AA37: Valuation date(s) | AB37: FX valuation start date | AG37: Redemption date | AI37: Valuation date(s) | AJ37: Initial valuation date | AN37: Interest determination date(s)
B38: FX valuation end date | D38: FX valuation end date | J38: Interval/Level? | V38: Initial valuation date | Y38: Initial valuation date | AA38: FX valuation start date | AB38: FX valuation end date | AH38: Initial valuation date | AJ38: Valuation date(s) | AK38: Initial valuation date | AP38: Initial valuation date
V39: Valuation date(s) | AA39: FX valuation end date | AG39: Initial valuation date | AH39: Valuation date(s) | AK39: Interest determination date(s) | AM39: Interest determination date(s)
AG40: Valuation date(s) | AK40: Valuation date(s)

Sheet Non-capital protected
B1: SE0005136918 | C1: NO0010730500 | D1: DK0030380761 | E1: SE0005224169 | F1: FI4000069414 | G1: SE0005936002 | H1: DK0030362009 | I1: SE0005136926 | J1: SE0005730983 | L1: SE0005649944 | M1: SE0005126323 | N1: SE0006599486 | O1: NO0010730518 | P1: NO0010744667 | Q1: SE0005991304 | R1: SE0005991213 | S1: SE0005991031 | T1: SE0005768785 | U1: SE0005768728 | V1: SE0005768595 | W1: SE0005650538 | X1: SE0005650140 | Y1: SE0005472180 | Z1: SE0005472149 | AA1: SE0005466265 | AB1: SE0005338167 | AC1: FI4000176961 | AD1: DK0030344379 | AE1: FI4000149877 | AF1: SE0004899896 | AG1: SE0005216892 | AH1: SE0005216926 | AI1: DK0030359567 | AJ1: SE0005216926 | AK1: SE0004898534 | AL1: FI4000090642 | AM1: DK0030362439 | AN1: SE0005650157 | AO1: SE0008587406 | AP1: SE0008587414
B2: Non-capital protected 1 | C2: Non-capital protected 2 | D2: Non-capital protected 3 | E2: Non-capital protected 4 | F2: Non-capital protected 5 | G2: Non-capital protected 6 | H2: Non-capital protected 7 | I2: Non-capital protected 8 | J2: Non-capital protected 9 | K2: Non-capital protected 10 | L2: Non-capital protected 11 | M2: Non-capital protected 12 | N2: Non-capital protected 13 | O2: Non-capital protected 14 | P2: Non-capital protected 15 | Q2: Non-capital protected 16 | R2: Non-capital protected 17 | S2: Non-capital protected 18 | T2: Non-capital protected 19 | U2: Non-capital protected 20 | V2: Non-capital protected 21 | W2: Non-capital protected 22 | X2: Non-capital protected 23 | Y2: Non-capital protected 24 | Z2: Non-capital protected 25 | AA2: Non-capital protected 26 | AB2: Non-capital protected 27 | AC2: Non-capital protected 28 | AD2: Non-capital protected 29 | AE2: Non-capital protected 30 | AF2: Non-capital protected 31 | AG2: Non-capital protected 32 | AH2: Non-capital protected 33 | AI2: Non-capital protected 34 | AJ2: Non-capital protected 35 | AK2: Non-capital protected 36 | AL2: Non-capital protected 37 | AM2: Non-capital protected 38 | AN2: Non-capital protected 39 | AO2: Non-capital protected 40 | AP2: Non-capital protected 41
A3: Level 1 | B3: Single underlying | C3: Multi underlying | D3: Single underlying | E3: Single underlying | F3: Single underlying | G3: Multi underlying, worst of | H3: Single underlying | I3: Single underlying | J3: Single underlying | K3: Multi underlying | L3: Single underlying | M3: Multi underlying, worst of | N3: Multi underlying, worst of | O3: Multi underlying | P3: Single underlying | Q3: Multi underlying, worst of | R3: Single underlying | S3: Multi underlying, worst of | T3: Multi underlying (relative difference between two underlying assets) | U3: Multi underlying, worst of | V3: Single underlying | W3: Multi underlying, worst of | X3: Single underlying | Y3: Multi underlying | Z3: Multi underlying, worst of | AA3: Multi underlying, worst of | AB3: Single underlying | AC3: Multi underlying | AD3: Single underlying FX (Currency pair) | AE3: Multi underlying | AF3: Multi underlying | AG3: Multi underlying, worst of | AH3: Single underlying TOM + Interest rate | AI3: Multi underlying | AJ3: Single underlying TOM | AK3: Multi underlying, relative difference between two assets | AL3: Multi underlying FX | AM3: Single underlying | AN3: Multi underlying, worst of | AO3: Single underlying + Underlying FX | AP3: Multi underlying (relative difference between two underlying assets)
A4: Level 2 | B4: Participation ratio | C4: Participation ratio | D4: Coupon | E4: Participation ratio | F4: Participation ratio | G4: Floating coupon (guaranteed) | H4: Participation ratio | I4: 2 Participation ratios | J4: Participation ratio | K4: Participation ratio | L4: Fixed coupon | M4: Fixed coupon | N4: Fixed coupon (guaranteed) | O4: Participation ratio | P4: Participation ratio | Q4: Participation ratio | R4: Participation ratio | S4: Participation ratio | T4: Participation ratio | U4: Floating coupon (guaranteed) | V4: Coupon | W4: Fixed coupon(guaranteed) | X4: Participation ratio | Y4: Coupon | Z4: Coupon | AA4: Coupon | AB4: Participation ratio | AC4: Coupon | AD4: Floating coupon | AE4: Fixed coupon (guaranteed) | AF4: Fixed coupon (guaranteed) | AG4: Coupon 1 and coupon 2 | AH4: Hybrid equity and interest rate | AI4: Participation ratio | AJ4: Participation ratio | AK4: TRP | AL4: Participation ratio | AM4: Participation ratio | AN4: Floating coupon (guaranteed) | AO4: Participation ratio | AP4: Participation ratio
A5: Level 3 | B5: European DIP Barrier | C5: All amount invested lost at negative performance (European barrier) | F5: Capped | G5: European DIP Barrier | H5: Capped | I5: Twin win | J5: European DIP Barrier | K5: European DIP Barrier | L5: American DIP Barrier | M5: European DIP barrier | N5: European DIP Barrier | O5: All amount invested lost at negative performance (European barrier) | P5: All amount invested lost at negative performance (European barrier) | Q5: European DIP Barrier | R5: European DIP Barrier | S5: Lock-in | T5: Risk barrier | U5: American DIP Barrier | V5: Participation ratio | W5: American DIP Barrier | X5: Capped | Z5: Participation ratio | AA5: Participation ratio | AB5: Flexo | AE5: Participation ratio | AF5: American Barrier | AG5: European barrier | AI5: Flexo | AK5: Floor and cap -CMS spread | AL5: Coupon | AM5: Flexo | AN5: American DIP Barrier | AO5: Capped
A6: Level 4 | B6: Quanto | C6: Quanto | D6: Quanto | E6: Quanto | F6: European DIP Barrier | G6: Quanto | H6: Quanto | I6: European DIP Barrier | J6: Flexo | K6: Quanto | L6: Quanto | M6: Quanto | N6: Quanto | O6: Capped | P6: Quanto | Q6: Quanto | R6: Quanto | S6: Risk barrier | U6: Quanto | V6: European barrier | W6: Quanto | X6: American DIP Barrier | Y6: European barrier | Z6: European DIP barrier | AA6: European DIP barrier | AC6: Quanto | AF6: Quanto | AG6: Quanto | AH6: Quanto | AJ6: Quanto | AN6: Quanto
A7: Level 5 | F7: Quanto | I7: Quanto | O7: Quanto | S7: Quanto | V7: Quanto | X7: Flexo | Y7: Quanto | Z7: Flexo | AA7: Quanto | AE7: Quanto
A8: EUSIPA-code | B8: 1330 | C8: 2100 | D8: 1320 | E8: 1310 | F8: 1240 | G8: 1250 | H8: 1240 | I8: 1340 | J8: 1330 | K8: 1330 | L8: 1320 | M8: 1320 | N8: 1250 | O8: 2110 | P8: 2100 | Q8: 1330 | R8: 1330 | S8: 1330 | T8: 1330 | U8: 1250 | V8: 1320 | W8: 1330 | X8: 1240 | Y8: 1320 | Z8: 1320 | AA8: 1320 | AL8: 1100 | AO8: 1240
A9: JIRA Code | B9: =INDEX('[1]JIRA-1'!$B:$B,MATCH(B2,'[1]JIRA-1'!$D:$D,0)) -> NORDEAML-827 | C9: =INDEX('[1]JIRA-1'!$B:$B,MATCH(C2,'[1]JIRA-1'!$D:$D,0)) -> NORDEAML-828 | D9: =INDEX('[1]JIRA-1'!$B:$B,MATCH(D2,'[1]JIRA-1'!$D:$D,0)) -> NORDEAML-829 | E9: =INDEX('[1]JIRA-1'!$B:$B,MATCH(E2,'[1]JIRA-1'!$D:$D,0)) -> NORDEAML-830 | F9: =INDEX('[1]JIRA-1'!$B:$B,MATCH(F2,'[1]JIRA-1'!$D:$D,0)) -> NORDEAML-831 | G9: =INDEX('[1]JIRA-1'!$B:$B,MATCH(G2,'[1]JIRA-1'!$D:$D,0)) -> NORDEAML-832 | H9: =INDEX('[1]JIRA-1'!$B:$B,MATCH(H2,'[1]JIRA-1'!$D:$D,0)) -> NORDEAML-833 | I9: =INDEX('[1]JIRA-1'!$B:$B,MATCH(I2,'[1]JIRA-1'!$D:$D,0)) -> NORDEAML-834 | ... AP9: =INDEX('[1]JIRA-1'!$B:$B,MATCH(AP2,'[1]JIRA-1'!$D:$D,0)) -> NORDEAML-872
A10: JIRA Issue ID | B10: =INDEX('[1]JIRA-1'!$C:$C,MATCH(B2,'[1]JIRA-1'!$D:$D,0)) -> 12095 | C10: =INDEX('[1]JIRA-1'!$C:$C,MATCH(C2,'[1]JIRA-1'!$D:$D,0)) -> 12096 | D10: =INDEX('[1]JIRA-1'!$C:$C,MATCH(D2,'[1]JIRA-1'!$D:$D,0)) -> 12097 | E10: =INDEX('[1]JIRA-1'!$C:$C,MATCH(E2,'[1]JIRA-1'!$D:$D,0)) -> 12098 | F10: =INDEX('[1]JIRA-1'!$C:$C,MATCH(F2,'[1]JIRA-1'!$D:$D,0)) -> 12099 | G10: =INDEX('[1]JIRA-1'!$C:$C,MATCH(G2,'[1]JIRA-1'!$D:$D,0)) -> 12100 | H10: =INDEX('[1]JIRA-1'!$C:$C,MATCH(H2,'[1]JIRA-1'!$D:$D,0)) -> 12101 | I10: =INDEX('[1]JIRA-1'!$C:$C,MATCH(I2,'[1]JIRA-1'!$D:$D,0)) -> 12102 | ... AP10: =INDEX('[1]JIRA-1'!$C:$C,MATCH(AP2,'[1]JIRA-1'!$D:$D,0)) -> 12140
A11: JIRA Product Feature | B11: EDIP | C11: FixedRedemption=0 | D11: DownsidePut | E11: DownsidePut | F11: EDIP | G11: EDIP | H11: DownsidePut | I11: TwinWin | J11: EDIP | K11: EDIP | L11: ADIP | M11: EDIP | N11: EDIP | O11: FixedRedemption=0 | P11: FixedRedemption=0 | Q11: EDIP | R11: EDIP | S11: EDIP | T11: Unmapped | U11: ADIP | V11: EDIP | W11: ADIP | X11: ADIP | Y11: EDIP | Z11: EDIP | AA11: EDIP | AB11: DownsidePut | AC11: DownsidePut | AD11: DownsidePut | AE11: DownsidePut | AF11: Unmapped | AG11: EDIP | AH11: Unmapped | AI11: Unmapped | AJ11: Unmapped | AK11: Unmapped | AL11: Unmapped | AM11: Unmapped | AN11: Unmapped | AO11: Unmapped | AP11: Unmapped
A12: JIRA Product Feature | B12: Call1 | C12: Call1 | D12: Best-of Coupon/Participation | E12: Call1 | F12: Call1 | G12: FloatingPayment | H12: Call1 | J12: Call1 | K12: Call1 | L12: Best-of Coupon/Participation | M12: Best-of Coupon/Participation | N12: FixedCoupon | O12: Call1 | P12: Call1 | Q12: Call1 | R12: Call1 | S12: DigitalObs Lock-In | T12: Special | U12: FloatingCoupon | V12: Best-of Coupon/Participation | W12: FixedCoupon | X12: Call1 | Y12: Best-of Coupon/Participation | Z12: Best-of Coupon/Participation | AA12: Best-of Coupon/Participation | AB12: Call1 | AC12: Best-of Coupon/Participation | AD12: FixedCoupon ParticipationxCoupon | AE12: FixedCoupon Interest | AF12: Special | AG12: Best-of Coupon/Participation IF ST > Strike
A13: JIRA Product Feature | F13: Call2 | H13: Call2 | O13: Call2 | P13: Call2 | S13: Special | X13: Call2 | Z13: Flexo | AB13: Flexo | AD13: Special | AI13: Flexo | AM13: Flexo
A14: JIRA Product Feature | X14: Flexo | AG14: Special
A15: Fixing needed? | B15: FinalFixing | C15: FinalFixing | D15: FinalFixing | E15: FinalFixing | F15: FinalFixing | G15: FinalFixing, FloatingFixings | H15: FinalFixing | I15: FinalFixing | J15: FinalFixing | K15: FinalFixing | L15: FinalFixing, BarrierEvent | M15: FinalFixing | N15: FinalFixing | O15: FinalFixing | P15: FinalFixing | Q15: FinalFixing | R15: FinalFixing | S15: FinalFixing, Lock-In-Events | U15: FinalFixing, FloatingFixing, BarrierEvent | V15: FinalFixing | W15: FinalFixing, BarrierEvent | X15: FinalFixing, BarrierEvent | Y15: FinalFixing | Z15: FinalFixing | AA15: FinalFixing | AB15: FinalFixing | AC15: FinalFixing | AD15: FinalFixing, UndObsFixings, | AE15: FinalFixing | AF15: NCPFixing31 | AG15: FinalFixing
A16: Type | B16: 1 b according to the MiFID (legal form?) | C16: 1 c according to the MiFID (legal form?) | D16: 1 b according to the MiFID (legal form?) | E16: 1 b according to the MiFID (legal form?) | F16: 1 b according to the MiFID (legal form?) | G16: 1 b according to the MiFID (legal form?) | H16: 1 b according to the MiFID (legal form?) | I16: 1 b according to the MiFID (legal form?) | J16: 1 b according to the MiFID (legal form?) | K16: 1 b according to the MiFID (legal form?) | L16: 1 b according to the MiFID (legal form?) | M16: 1 b according to the MiFID (legal form?) | N16: 1 b according to the MiFID (legal form?) | O16: 1 c according to the MiFID (legal form?) | P16: 1 b according to the MiFID (legal form?) | Q16: 1 b according to the MiFID (legal form?) | R16: 1 b according to the MiFID (legal form?) | S16: 1 b according to the MiFID (legal form?) | T16: 1 b according to the MiFID (legal form?) | U16: 1 b according to the MiFID (legal form?) | V16: 1 b according to the MiFID (legal form?) | W16: 1 b according to the MiFID (legal form?) | X16: 1 b according to the MiFID (legal form?) | Y16: 1 b according to the MiFID (legal form?) | Z16: 1 b according to the MiFID (legal form?) | AA16: 1 b according to the MiFID (legal form?) | AB16: 1 b according to the MiFID (legal form?) | AC16: 1 b according to the MiFID (legal form?) | AD16: 1 b according to the MiFID (legal form?) | AE16: 1 b according to the MiFID (legal form?) | AF16: 1 b according to the MiFID (legal form?) | AG16: 1 b according to the MiFID (legal form?) | AH16: 1 b according to the MiFID (legal form?) | AI16: 1 b according to the MiFID (legal form?) | AJ16: 1 b according to the MiFID (legal form?) | AK16: 1 b according to the MiFID (legal form?) | AL16: 1 b according to the MiFID (legal form?) | AM16: 1 b according to the MiFID (legal form?) | AN16: 1 b according to the MiFID (legal form?) | AO16: 1 b according to the MiFID (legal form?) | AP16: 1 b according to the MiFID (legal form?)
B17: Outperformance Bonus Certificate | C17: Warrant | D17: Bonus Certificate | E17: Outperformance Certificate | F17: Capped Outperformance Certificate | G17: Capped Bonus Certificate | H17: Capped Outperformance Certificate | I17: Twin-Win Certificate | J17: Outperformance Bonus Certificate | K17: Outperformance Bonus Certificate | L17: Bonus Certificate | M17: Bonus Certificate | N17: Capped Bonus Certificate | O17: Spread Warrant | P17: Warrant | Q17: Outperformance Bonus Certificate | R17: Outperformance Bonus Certificate | S17: Outperformance Bonus Certificate | T17: Outperformance Bonus Certificate | U17: Capped Bonus Certificate | V17: Bonus Certificate | W17: Outperformance Bonus Certificate | X17: Capped Outperformance Certificate | Y17: Bonus Certificate | Z17: Bonus Certificate | AA17: Bonus Certificate | AB17: Outperformance Certificate | AC17: Bonus Certificate | AD17: Outperformance Certificate | AE17: Outperformance Certificate | AF17: Outperformance Certificate | AG17: Twin-Win Certificates | AH17: Outperformance Certificate | AI17: Outperformance Certificate | AJ17: Outperformance Certificate | AK17: Outperformance Certificate | AL17: Uncapped Capital Protection | AM17: Outperformance Certificate | AN17: Outperformance Bonus Certificate | AO17: Capped Outperformance Certificate | AP17: Outperformance Certificates
B18: Underlying asset(s) (initial price) | C18: Underlying asset(s) (initial price) | D18: Underlying asset(s) (initial price) | E18: Underlying asset(s) (initial price) | F18: Underlying asset(s) (initial price) | G18: Underlying asset(s) (initial price) | H18: Underlying asset(s) (initial price) | I18: Underlying asset(s) (initial price) | J18: Underlying asset(s) (initial price) | K18: Underlying asset(s) (initial price) | L18: Underlying asset(s) (initial price) | M18: Underlying asset(s) (initial price) | N18: Underlying asset(s) (initial price) | O18: Underlying asset(s) (initial price) | P18: Underlying asset(s) (initial price) | Q18: Underlying asset(s) (initial price) | R18: Underlying asset(s) (initial price) | S18: Underlying asset(s) (initial price) | T18: Underlying asset(s) (initial price) | U18: Underlying asset(s) (initial price) | V18: Underlying asset(s) (initial price) | W18: Underlying asset(s) (initial price) | X18: Underlying asset(s) (initial price) | Y18: Underlying asset(s) (initial price) | Z18: Underlying asset(s) (initial price) | AA18: Underlying asset(s) (initial price) | AB18: Underlying asset(s) (initial price) | AC18: Underlying asset(s) (initial price) | AD18: Underlying asset(s) (initial price) | AE18: Underlying asset(s) (initial price) | AF18: Underlying asset(s) (initial price) | AG18: Underlying asset(s) (initial price) | AH18: Underlying asset(s) (initial price) | AI18: Underlying asset(s) (initial price) | AJ18: Underlying asset(s) (initial price) | AK18: Underlying asset(s) (initial price) | AL18: Underlying asset(s) (initial price) | AM18: Underlying asset(s) (initial price) | AN18: Underlying asset(s) (initial price) | AO18: Underlying asset(s) (initial price) | AP18: Underlying asset(s) (initial price)
A19: How the investment works | B19: The objective is to invest in a note that will benefit from a rising market. | C19: The objective is to invest in a note that will give a much higher return than the underlying asset, when the price of the underlying asset is rising. | D19: The objective is to invest in a note that, at the minimum, will pay a fixed return when the price of the underlying asset is rising. | E19: The objective is to invest in a note that will benefit from a rising market. | F19: The objective is to invest in a note where you believe that the price of the underlying asset will rise, but not over a certain level (performance cap multiplied by participation ratio). | G19: The objective is to invest in a note with floating interest payments. | H19: The objective is to invest in a note where you believe that the price of the underlying asset will rise, but not over a certain level (performance cap multiplied by participation ratio). | I19: The objective is to invest in a note where you believe that the performance of the underlying asset will be within a predefined interval. | J19: The objective is to invest in a note that will benefit from a rising market. | K19: The objective is to invest in a note that will benefit from a rising market. | L19: The objective is to invest in a note that, at the minimum, will pay a fixed return if the price of the underlying asset never has been lower than a predefined level during the lifetime if the investment. | M19: The objective is to invest in a note that, at the minimum, will pay a fixed return if the price of the worst performing underlying asset is higher than a predefined level on the valuation date. | N19: The objective is to invest in a note with fixed interest payments. | O19: The objective is to invest in a note that will benefit from a rising market. | P19: The objective is to invest in a note where you believe that the price of the underlying asset will rise, but not over a certain level (performance cap multiplied by participation ratio). | Q19: The objective is to invest in a note that will benefit from a rising market. | R19: The objective is to invest in a note that will benefit from a rising market. | S19: The objective is to invest in a note that will give a higher return than the underlying asset, when the price of the underlying asset is rising, and at the same time secure positive performance at certain levels. | T19: The objective is to invest in a note that will benefit from the relative performance between two underlying assets. | U19: The objective is to invest in a note with floating interest payments. | V19: The objective is to invest in a note that, at the minimum, will pay a fixed return if the price of the underlying asset is higher than a predefined level on the valuation date. | W19: The objective is to invest in a note with fixed interest payments. | X19: The objective is to invest in a note where you believe that the price of the underlying asset will rise, but not over a certain level (performance cap multiplied by participation ratio). | Y19: The objective is to invest in a note that, at the minimum, will pay a fixed return if the price of the underlying asset is higher than a predefined level on the valuation date. | Z19: The objective is to invest in a note that, at the minimum, will pay a fixed return if the price of the worst performing underlying asset is higher than a predefined level on the valuation date. | AA19: The objective is to invest in a note that, at the minimum, will pay a fixed return if the price of the worst performing underlying asset is higher than a predefined level on the valuation date. | AB19: The objective is to invest in a note that will benefit from a rising market. | AC19: The objective is to invest in a note that, at the minimum, will pay a fixed return if the price of the underlying asset is higher than a predefined level on the valuation date. | AD19: The objective is to invest in a note with floating interest payments. | AE19: The objective is to invest in a note that will give fixed interest payments and a higher return than the underlying asset, when the price of the underlying asset is rising. | AF19: The objective is to invest in a note with fixed interest payments. | AG19: The objective is to invest in a note that will pay a fixed return if the price of the underlying asset is above a predefined level. | AH19: The objective is to benefit from the turn of the month strategy and to benefit from rising interest rates. | AI19: The objective is to invest in a note that will give a higher return than the underlying asset, when the price of the underlying asset is rising. | AJ19: The objective is to benefit from the turn of the month strategy and to invest in a note that will give a higher return than the underlying asset, when the price of the underlying asset is rising. | AK19: The objective is to invest in a note that will benefit from the relative performance between two underlying assets. | AL19: The objective is to invest in a note that will pay a coupon. | AM19: The objective is to invest in a note that will give a higher return than the underlying asset, when the price of the underlying asset is rising. | AN19: The objective is to invest in a note with floating interest payments. | AO19: The objective is to invest in a note where you believe that the price of the underlying asset will rise, but not over a certain level (performance cap multiplied by participation ratio). And that a foreign currency will strengthen against a local currency. | AP19: The objective is to invest in a note that will benefit from the relative performance between two underlying assets.
B20: The return of the investment depends on the performance of the underlying asset during the lifetime of the investment. | C20: The return of the investment depends on the performance of a basket of underlying assets during the lifetime of the investment. | D20: The return of the investment depends on the performance of the underlying asset during the lifetime of the investment. | E20: The return of the investment depends on the performance of the underlying asset during the lifetime of the investment. | F20: The return of the investment depends on the performance of the underlying asset during the lifetime of the investment. | G20: The return of the investment depends on the performance of a basket of underlying assets during the lifetime of the investment. | H20: The return of the investment depends on the performance of the underlying asset during the lifetime of the investment. | I20: The return of the investment depends on the performance of the underlying asset during the lifetime of the investment. | J20: The return of the investment depends on the performance of the underlying asset during the lifetime of the investment. | K20: The return of the investment depends on the performance of a basket of underlying assets during the lifetime of the investment. | L20: The return of the investment depends on the performance of the underlying asset during the lifetime of the investment. | M20: The return of the investment depends on the performance of a basket of underlying assets during the lifetime of the investment. | N20: The return of the investment depends on the performance of a basket of underlying assets during the lifetime of the investment. | O20: The return of the investment depends on the performance of a basket of underlying assets during the lifetime of the investment. | P20: The return of the investment depends on the performance of an underlying asset during the lifetime of the investment. | Q20: The return of the investment depends on the performance of a basket of underlying assets during the lifetime of the investment. | R20: The return of the investment depends on the performance of an underlying asset during the lifetime of the investment. | S20: The return of the investment depends on the performance of a basket of underlying assets during the lifetime of the investment. | T20: The return of the investment depends on the relative difference between two underlying assets during the lifetime of the investment. | U20: The return of the investment depends on the performance of a basket of underlying assets during the lifetime of the investment. | V20: The return of the investment depends on the performance of the underlying asset during the lifetime of the investment. | W20: The return of the investment depends on the performance of a basket of underlying assets during the lifetime of the investment. | X20: The return of the investment depends on the performance of the underlying asset during the lifetime of the investment. | Y20: The return of the investment depends on the performance of a basket of underlying assets during the lifetime of the investment. | Z20: The return of the investment depends on the performance of a basket of underlying assets during the lifetime of the investment. | AA20: The return of the investment depends on the performance of a basket of underlying assets during the lifetime of the investment. | AB20: The return of the investment depends on the performance of the underlying asset during the lifetime of the investment. | AC20: The return of the investment depends on the performance of a basket of underlying assets during the lifetime of the investment. | AD20: The return of the investment depends on the performance of the underlying asset during the lifetime of the investment. | AE20: The return of the investment depends on the performance of a basket of underlying assets during the lifetime of the investment. | AF20: The return of the investment depends on the performance of a basket of underlying assets during the lifetime of the investment. | AG20: The return of the investment depends on the performance of a basket of underlying assets during the lifetime of the investment. | AH20: The return of the investment depends on the performance of the underlying assets during the lifetime of the investment. | AI20: The return of the investment depends on the performance of a basket of underlying assets during the lifetime of the investment. | AJ20: The return of the investment depends on the performance of an underlying asset during the lifetime of the investment. | AK20: The return of the investment depends on the relative difference between two underlying interest rates. | AL20: The return of the investment depends on the performance of a basket of underlying assets during the lifetime of the investment. | AM20: The return of the investment depends on the performance of an underlying asset during the lifetime of the investment. | AN20: The return of the investment depends on the performance of a basket of underlying assets during the lifetime of the investment. | AO20: The return of the investment depends both on the performance of the underlying asset and on currency fluctuations in the currency exposure during the lifetime of the investment. | AP20: The return of the investment depends on the relative difference between two underlying assets during the lifetime of the investment.
B21: If, on the valuation date, the underlying asset has had a positive performance the note will pay the nominal amount plus the nominal amount multiplied by the performance of the underlying asset multiplied by the participation ratio, on the redemption date. | C21: If, on the valuation date, the basket has had a positive performance the note will pay the nominal amount multiplied by the performance of underlying basket multiplied by the participation ratio, on the redemption date. | D21: If, on the valuation date, the underlying asset has had a positive performance the note will pay the nominal amount plus the nominal amount multiplied by the highest of (i) the performance of the underlying asset and (ii) the coupon, on the redemption date. | E21: If, on the valuation date, the underlying asset has had a positive performance the note will pay the nominal amount plus the nominal amount multiplied by the performance of underlying asset multiplied by the participation ratio, on the redemption date. | F21: If, on the valuation date, the underlying asset has had a positive performance the note will pay the nominal amount plus the nominal amount multiplied by the performance of the underlying asset multiplied by the participation ratio, on the redemption date. When calculating the performance, the performance has a cap. | G21: The note will pay a floating interest (interest margin plus reference rate), calculated on the nominal amount, on each interest payment date. | H21: If, on the valuation date, the underlying asset has had a positive performance the note will pay the nominal amount plus the nominal amount multiplied by the performance of the underlying asset multiplied by the participation ratio, on the redemption date. When calculating the performance, the performance has a cap. | I21: If, on the valuation date, the underlying asset has had a positive performance the note will pay the nominal amount plus the nominal amount multiplied by the performance of the underlying asset multiplied by participation ratio 1, on the redemption date. | J21: If, on the valuation date, the underlying asset has had a positive performance the note will pay the nominal amount plus the nominal amount multiplied by the performance of the underlying asset multiplied by the participation ratio, on the redemption date. Currency fluctuations will also affect the return of the investment. | K21: If, on the valuation date, the basket has had a positive performance the note will pay the nominal amount plus the nominal amount multiplied by the performance of the basket multiplied by the participation ratio, on the redemption date. | L21: If the price of the underlying asset, from the initial valuation date to, and including, the end valuation date, never has been lower than the predefined barrier, the note will pay the nominal amount plus the nominal amount multiplied by the highest of (i) the performance of the underlying asset and (ii) the coupon, on the redemption date. | M21: If, on the valuation date, the worst performing underlying asset is at or above the predefined barrier, the note will pay the nominal amount plus the nominal amount multiplied by the highest of (i) the performance of the basket and (ii) the coupon, on the redemption date. | N21: The note will pay a fixed interest, calculated on the nominal amount, on each interest payment date. | O21: If, on the valuation date, the basket has had a positive performance the note will pay the nominal amount multiplied by the performance of the basket multiplied by the participation ratio, on the redemption date. When calculating the performance, the performance has a cap. | P21: If, on the valuation date, the underlying asset has had a positive performance the note will pay the nominal amount multiplied by the performance of underlying asset multiplied by the participation ratio, on the redemption date. | Q21: If the basket has had a positive performance, the note will pay the nominal amount plus the nominal amount multiplied by the performance of the basket multiplied by the participation ratio, on the redemption date. | R21: If, on the valuation date, the underlying asset has had a positive performance the note will pay the nominal amount plus the nominal amount multiplied by the performance of the underlying asset multiplied by participation ratio 1, on the redemption date. | S21: If, on a valuation date, the performance of the basket has reached one of the lock-in levels, the return of the note will be locked at twice of the highest lock-in level that has been reached multiplied by the participation ratio. | T21: If, on the valuation date, underlying asset 1 is at or above the predefined barrier the note will pay the nominal amount plus the highest of (i) the nominal amount multiplied by the relative difference between the underlying assets multiplied by the participation ratio and (ii) zero, on the redemption date. | U21: The note will pay a floating interest (interest margin plus reference rate), calculated on the nominal amount, on each interest payment date. | V21: If, on the valuation date, the price of the underlying asset is at or above the predefined barrier the note will pay the nominal amount plus the nominal amount multiplied by the highest of (i) the performance of the underlying asset multiplied by the participation ratio and (ii) the coupon, on the redemption date. | W21: The note will pay a fixed interest, calculated on the nominal amount, on each interest payment date. | X21: If the underlying asset has had a positive performance, the note will pay the nominal amount plus the nominal amount multiplied by the performance of the underlying asset multiplied by the participation ratio, on the redemption date. When calculating the performance, the performance has a cap. Currency fluctuations will also affect the return of the investment. | Y21: If, on the valuation date, the basket is at or above the predefined barrier the note will pay the nominal amount plus the nominal amount multiplied by the highest of (i) the performance of the basket and (ii) the coupon, on the redemption date. | Z21: If, on the valuation date, the worst performing underlying asset is at or above the predefined barrier, the note will pay the nominal amount plus the nominal amount multiplied by the highest of (i) the performance of the basket multiplied by the participation ratio multiplied by currency fluctuations and (ii) the coupon, on the redemption date. | AA21: If, on the valuation date, the worst performing underlying asset is at or above the predefined barrier, the note will pay the nominal amount plus the nominal amount multiplied by the highest of (i) the performance of the basket multiplied by the participation ratio and (ii) the coupon, on the redemption date. | AB21: If, on the valuation date, the underlying asset has had a positive performance the note will pay the nominal amount plus the nominal amount multiplied by the performance of the underlying asset multiplied by the participation ratio, on the redemption date. Currency fluctuations will also affect the return of the investment. | AC21: If, on the valuation date, the basket has had a positive performance the note will pay the nominal amount plus the nominal amount multiplied by the highest of (i) the performance of the underlying asset and (ii) the coupon on the redemption date. | AD21: The note will pay a coupon (coupon multiplied by the performance of the underlying asset), calculated on the nominal amount, on each interest payment date. | AE21: The note will pay a fixed interest, calculated on the nominal amount, on each interest payment date. | AF21: The note will pay a fixed interest, calculated on the adjusted nominal amount, on each interest payment date. | AG21: If, on the valuation date, all underlying assets in the basket has had a positive performance the note will pay the nominal amount plus the nominal amount multiplied by the highest of (i) the performance of the basket and (ii) coupon 1, on the redemption date. | AH21: If, on the valuation date, the underlying index has had a positive performance the note will pay the nominal amount plus the nominal amount multiplied by the performance of the underlying index multiplied by the participation ratio, on the redemption date. | AI21: If the basket has a positive performance, the note will pay the nominal amount plus the nominal amount multiplied by the performance of the underlying basket multiplied by the participation ratio, on the redemption date. Currency fluctuations will also affect the return of the investment. | AJ21: If the underlying asset has a positive performance, the note will pay the nominal amount plus the nominal amount multiplied by the performance of the underlying asset multiplied by the participation ratio, on the redemption date. | AK21: The redemption amount will depend on the 10 Y EUR Rate and the 30 Y EUR Rate as observed on the valuation date. On the valuation date, the performance will be calculated as (i) the highest of zero or the difference between the performance cap and the 30 Y minus the 10 Y EUR Rate minus (ii) the highest of zero or the difference between the performance floor and the 30 Y minus the 10 Y EUR Rate, the sum of which is multiplied with the participation ratio. | AL21: If the basket has a positive performance, the note will pay the nominal amount plus the nominal amount multiplied by the coupon plus the nominal amount multiplied by the performance of the basket multiplied, on the redemption date. | AM21: If the underlying asset has a positive performance, the note will pay the nominal amount plus the nominal amount multiplied by the performance of the underlying asset multiplied by the participation ratio, on the redemption date. Currency fluctuations will also affect the return of the investment. | AN21: The note will pay a floating interest (interest margin plus reference rate), calculated on the nominal amount, on each interest payment date. | AO21: If, on the valuation date, the underlying asset has had a positive performance the value of the note will be calculated in two steps. First as the nominal amount plus the nominal amount multiplied by the performance of the underlying asset multiplied by the participation ratio. When calculating the performance, the performance has a cap. In the second step, the total sum from the first step will be multiplied by the currency exchange rate changes. The sum of step two will be paid on the redemption date. | AP21: On the redemption date, the note will pay the sum of the performance of underlying asset 1 multiplied by the participation ratio minus the performance of underlying asset 2, multiplied by the nominal amount plus the nominal amount.
B22: If, on the valuation date, the underlying asset has had a negative performance, but is at or above the predefined barrier, the note will pay the nominal amount on the redemption date. | C22: If, on the valuation date, the basket has had an unchanged or negative performance the whole amount invested will be lost. | D22: If, on the valuation date, the underlying asset has had a negative performance the note will pay the nominal amount reduced by the negative performance of the underlying asset on the redemption date. | E22: If, on the valuation date, the underlying asset has had a negative performance the note will pay the nominal amount reduced by the negative performance of the underlying asset, on the redemption date. | F22: If, on the valuation date, the underlying asset has had a negative performance, but is at or above the predefined barrier, the note will pay the nominal amount on the redemption date. | G22: If, on the valuation date, the worst performing underlying asset is at or above the predefined barrier, the note will pay the nominal amount on the redemption date. | H22: If, on the valuation date, the underlying asset has had a negative performance the note will pay the nominal amount reduced by the negative performance of the underlying asset on the redemption date. | I22: If, on the valuation date, the underlying asset has had a negative performance but is at or above the predefined barrier, the note will still have a positive return. The note will then pay the nominal amount plus the nominal amount multiplied by the absolute performance of the underlying asset multiplied by participation ratio 2, on the redemption date. | J22: If, on the valuation date, the underlying asset has had a negative performance but is at or above the predefined barrier, the note will pay the nominal amount on the redemption date. | K22: If, on the valuation date, the basket has had a negative performance but is at or above the predefined barrier, the note will pay the nominal amount on the redemption date. | L22: If the price of the underlying asset, from the initial valuation date to, and including, the end valuation date, has been lower than the predefined barrier, the note will pay the nominal amount plus the nominal amount multiplied by the performance of the underlying asset on the redemption date. | M22: If, on the valuation date, the worst performing underlying asset is below the barrier, the note will pay the nominal amount reduced by the negative performance of the worst performing underlying asset on the redemption date. | N22: If, on the valuation date, the worst performing underlying asset is at or above the predefined barrier, the note will pay the nominal amount on the redemption date. | O22: If, on the valuation date, the basket has had a negative performance the whole amount invested will be lost. | P22: If, on the valuation date, the underlying asset has had a negative performance the whole amount invested will be lost. | Q22: If the worst performing underlying asset has had a negative performance, but is at or above the predefined barrier on the valuation date, the note will pay the nominal amount on the redemption date. | R22: If, on the valuation date, the underlying asset has had a negative performance, but is at or above the predefined barrier on the valuation date, the note will pay the nominal amount on the redemption date. | S22: If, on the last valuation date, the worst performing underlying asset is at or above the predefined barrier, the note will pay the nominal amount plus the nominal amount multiplied by twice of the highest lock-in level that has been reached multiplied by the participation rate on the redemption date. If no lock-in level has been reached, the note will pay the nominal amount. | T22: If, on the valuation date, underlying asset 1 is below the barrier and the relative difference between the underlying assets is positive, the note will pay the nominal amount reduced by the negative performance of underlying asset 1 plus the relative difference between the underlying assets multiplied by the participation ratio multiplied by the nominal amount, on the redemption date. | U22: If the price of the worst performing underlying asset, from the initial valuation date to, and including, the end valuation date, never has been lower than the predefined barrier, the note will pay the nominal amount on the redemption date. | V22: If, on the valuation date, the price of the underlying asset is below the barrier, the note will pay the nominal amount reduced by the negative performance of the underlying asset on the redemption date. | W22: If the price of the worst performing underlying asset, from the initial valuation date to, and including, the end valuation date, never has been lower than the predefined barrier, the note will pay the nominal amount on the redemption date. | X22: If the underlying asset has had a negative performance, but has never, from the initial valuation date to, and including, the end valuation date, had a price lower than the predefined barrier, the note will pay the nominal amount on the redemption date. | Y22: If, on the valuation date, the basket is below the barrier, the note will pay the nominal amount reduced by the negative performance of the underlying basket on the redemption date. | Z22: If, on the valuation date, the worst performing underlying asset is below the barrier, the note will pay the nominal amount reduced by the negative performance of the worst performing underlying asset on the redemption date. | AA22: If, on the valuation date, the worst performing underlying asset is below the barrier, the note will pay the nominal amount reduced by the negative performance of the worst performing underlying asset on the redemption date. | AB22: If, on the valuation date, the underlying asset has had a negative performance the note will pay the nominal amount reduced by the negative performance of the underlying asset on the redemption date. | AC22: If, on the valuation date, the basket has had a negative performance the note will pay the nominal amount reduced by the negative performance of the underlying basket on the redemption date. | AD22: If, on the valuation date, the underlying asset has had a positive performance the note will pay the nominal amount plus the nominal amount multiplied by the performance of the underlying asset, on the redemption date. | AE22: If, on the valuation date, the basket has had a positive performance the note will pay the nominal amount plus the nominal amount multiplied by the performance of the basket, on the redemption date. | AF22: If none of the underlying assets in the basket, from the initial valuation date to, and including, the end valuation date, has had a price lower than the predefined barrier, the note will pay the nominal amount on the redemption date. | AG22: If, on the valuation date, the worst performing underlying asset has had a negative performance but is at or above the predefined barrier, the note will pay the nominal amount plus the nominal amount multiplied by coupon 2 on the redemption date. | AH22: The performance of the underlying index is determined by a predefined strategy – turn of the month. Turn of the month means that the note is exposed to each of the underlying index only during a predefined number of days per month. Other times the note is invested in short-term interest rates. | AI22: If the basket has an unfavourable performance, the note will pay the nominal amount minus the nominal amount multiplied by the performance of the basket, on the redemption date. The negative basket performance has a maximum loss. Currency fluctuations will also affect the return of the investment. | AJ22: The performance of the underlying asset is determined by a predefined strategy – turn of the month. Turn of the month means that the note is exposed to the underlying asset only during a predefined number of days per month. | AK22: If the relative difference between the 30 Y EUR Rate and the 10 Y EUR Rate is at or above the performance cap, the note will pay the nominal amount plus the nominal amount multiplied by the target redemption amount, on the redemption date. | AL22: If the basket has an negative performance, the note will pay the nominal amount multiplied by the coupon plus the nominal amount reduced by the negative performance of the basket, on the redemption date. | AM22: If the underlying asset has an unfavourable performance, the note will pay the nominal amount minus the nominal amount multiplied by the performance of the underlying asset, on the redemption date. The negative performance of the underlying asset has a maximum loss. Currency fluctuations will also affect the return of the investment. | AN22: If the worst performing underlying asset, from the initial valuation date to, and including, the end valuation date, never has been lower than the predefined barrier, the note will pay the nominal amount on the redemption date. | AO22: If, on the valuation date, the underlying asset has had a negative performance the note will pay the nominal amount reduced by the negative performance of the underlying asset multiplied by the currency exchange rate changes, on the redemption date.
B23: If the underlying asset is below the barrier on the valuation date, the note will pay the nominal amount reduced by the negative performance of the underlying asset on the redemption date. | F23: If the underlying asset is below the barrier on the valuation date, the note will pay the nominal amount reduced by the negative performance of the underlying asset on the redemption date. | G23: If, on the valuation date, the worst performing underlying asset is below the barrier, the note will pay the nominal amount reduced by the negative performance of the worst performing underlying asset on the redemption date. | I23: If the underlying asset is below the barrier on the valuation date, the note will pay the nominal amount reduced by the negative performance of the underlying asset on the redemption date. | J23: If the underlying asset is below the barrier on the valuation date, the note will pay the nominal amount reduced by the negative performance of the underlying asset on the redemption date. | K23: If the basket is below the barrier on the valuation date, the note will pay the nominal amount reduced by the negative performance of the underlying basket on the redemption date. | N23: If, on the valuation date, the worst performing underlying asset is below the barrier, the note will pay the nominal amount reduced by the negative performance of the worst performing underlying asset on the redemption date. | Q23: If the worst performing underlying asset is below the barrier on the valuation date, the note will pay the nominal amount reduced by the negative performance of the worst performing underlying asset on the redemption date. | R23: If the underlying asset is below the barrier on the valuation date, the note will pay the nominal amount reduced by the negative performance minus the difference between the nominal amount and the barrier multiplied by participation ratio 2 on the redemption date. | S23: If, on the last valuation date, the worst performing asset is below the predefined barrier, the note will pay the nominal amount reduced by the negative performance of the worst performing underlying asset plus the nominal amount multiplied by twice of the highest lock-in level that has been reached multiplied by the participation rate, on the redemption date. | T23: If, on the valuation date, underlying asset 1 is below the barrier and the relative difference between the underlying assets is negative, the note will pay the nominal amount reduced by the performance of underlying asset 1 on the redemption date. | U23: If the price of the worst performing underlying asset, from the initial valuation date to, and including, the end valuation date, has been lower than the predefined barrier, the note will pay the nominal amount plus the nominal amount multiplied by the performance of that underlying asset on the redemption date. | W23: If the price of the worst performing underlying asset, from the initial valuation date to, and including, the end valuation date, has been lower than the predefined barrier and the worst performing asset has had a positive performance on the final valuation date, the note will pay the nominal amount on the redemption date. | X23: If the underlying asset has had a negative performance, and has, from the initial valuation date to, and including, the end valuation date, had a price lower than the predefined barrier, the note will pay the nominal amount reduced by the negative performance of the underlying asset on the redemption date. | AD23: If, on the valuation date, the underlying asset has had a negative performance the note will pay the nominal amount reduced by the negative performance of the underlying asset on the redemption date. | AE23: If, on the valuation date, the underlying basket has had a negative performance the note will pay the nominal amount reduced by the negative performance of the basket on the redemption date. | AF23: If one or more of the underlying assets in the basket, from the initial valuation date to, and including, the end valuation date, has been lower than the predefined barrier, the nominal amount will be reduced by 1 divided by the number of underlying assets in the basket for each underlying asset that has been lower than the barrier. The note will pay the adjusted nominal amount on the redemption date. | AG23: If the worst performing underlying asset is below the barrier on the valuation date, the note will pay the nominal amount reduced by the negative performance of the worst performing underlying asset on the redemption date. | AH23: If, on the valuation date, the underlying index has had a negative performance the note will pay the nominal amount reduced by the negative performance of the underlying assets on the redemption date. | AJ23: If the underlying asset has a negative performance, the note will pay the nominal amount reduced by the negative performance of the underlying asset, on the redemption date. | AK23: If the relative difference is below the performance cap, the note will pay the nominal amount plus the nominal amount multiplied by the target redemption amount minus the performance, on the redemption date. | AN23: If the worst performing underlying asset, from the initial valuation date to, and including, the end valuation date, has been lower than the predefined barrier, there are two possible scenarios: i) On the end valuation date, the worst performing asset has had a positive performance. The note will then pay the nominal amount on the redemption date. ii) On the end valuation date, the worst performing underlying asset has had a negative performance. The note will then pay the nominal amount reduced by the negative performance of the worst performing underlying asset, on the redemption date.
A24: Upside | B24: =VLOOKUP(B21,Tabelle1!$A$2:$B$35,2,0) -> #VALUE! | C24: =VLOOKUP(C21,Tabelle1!$A$2:$B$35,2,0) -> 100% + (Performance * Participation) | D24: =VLOOKUP(D21,Tabelle1!$A$2:$B$35,2,0) -> #VALUE! | E24: =VLOOKUP(E21,Tabelle1!$A$2:$B$35,2,0) -> 100% + (Performance * Participation) | F24: =VLOOKUP(F21,Tabelle1!$A$2:$B$35,2,0) -> #VALUE! | G24: =VLOOKUP(G21,Tabelle1!$A$2:$B$35,2,0) -> ### | H24: =VLOOKUP(H21,Tabelle1!$A$2:$B$35,2,0) -> #VALUE! | I24: =VLOOKUP(I21,Tabelle1!$A$2:$B$35,2,0) -> ### | ... AP24: =VLOOKUP(AP21,Tabelle1!$A$2:$B$35,2,0) -> 100% + Performance1 * Participation - Performance2
A25: Downside | B25: =VLOOKUP(B22,Tabelle3[],2,0) -> (Performance * Participation); DI BARRIER AT MATURITY | C25: =VLOOKUP(C22,Tabelle3[],2,0) -> - 100% | D25: =VLOOKUP(D22,Tabelle3[],2,0) -> (Performance * Participation) | E25: =VLOOKUP(E22,Tabelle3[],2,0) -> (Performance * Participation) | F25: =VLOOKUP(F22,Tabelle3[],2,0) -> (Performance * Participation); DI BARRIER AT MATURITY | G25: =VLOOKUP(G22,Tabelle3[],2,0) -> (Performance * Participation); DI BARRIER AT MATURITY | H25: =VLOOKUP(H22,Tabelle3[],2,0) -> (Performance * Participation) | I25: =VLOOKUP(I22,Tabelle3[],2,0) -> #VALUE! | ... AP25: =VLOOKUP(AP22,Tabelle3[],2,0) -> #N/A
A28: Key figures: | B28: Minimum subscription amount | C28: Minimum subscription amount | D28: Minimum subscription amount | E28: Minimum subscription amount | F28: Minimum subscription amount | G28: Minimum subscription amount | H28: Minimum subscription amount | I28: Minimum subscription amount | J28: Minimum subscription amount | K28: Minimum subscription amount | L28: Minimum subscription amount | M28: Minimum subscription amount | N28: Minimum subscription amount | O28: Minimum subscription amount | P28: Minimum subscription amount | Q28: Minimum subscription amount | R28: Minimum subscription amount | S28: Minimum subscription amount | T28: Minimum subscription amount | U28: Minimum subscription amount | V28: Minimum subscription amount | W28: Minimum subscription amount | X28: Minimum subscription amount | Y28: Minimum subscription amount | Z28: Minimum subscription amount | AA28: Minimum subscription amount | AB28: Minimum subscription amount | AD28: Minimum subscription amount | AE28: Minimum subscription amount | AF28: Minimum subscription amount | AG28: Minimum subscription amount | AH28: Minimum subscription amount | AI28: Minimum subscription amount | AJ28: Minimum subscription amount | AM28: Minimum subscription amount | AN28: Minimum subscription amount | AO28: Minimum subscription amount | AP28: Minimum subscription amount
B29: Subscription end date | C29: Subscription end date | D29: Subscription end date | E29: Subscription end date | F29: Subscription end date | G29: Subscription end date | H29: Subscription end date | I29: Subscription end date | J29: Subscription end date | K29: Subscription end date | L29: Subscription end date | M29: Subscription end date | N29: Subscription end date | O29: Subscription end date | P29: Subscription end date | Q29: Subscription end date | R29: Subscription end date | S29: Subscription end date | T29: Subscription end date | U29: Subscription end date | V29: Subscription end date | W29: Subscription end date | X29: Subscription end date | Y29: Subscription end date | Z29: Subscription end date | AA29: Subscription end date | AB29: Subscription end date | AC29: Minimum subscription amount | AD29: Subscription end date | AE29: Subscription end date | AF29: Subscription end date | AG29: Subscription end date | AH29: Subscription end date | AI29: Subscription end date | AJ29: Subscription end date | AK29: Minimum subscription amount | AL29: Minimum subscription amount | AM29: Subscription end date | AN29: Subscription end date | AO29: Subscription end date | AP29: Subscription end date
B30: Issue price | C30: Issue price | D30: Issue price | E30: Issue price | F30: Issue price | G30: Issue price | H30: Issue price | I30: Issue price | J30: Issue price | K30: Issue price | L30: Issue price | M30: Issue price | N30: Issue price | O30: Issue price | P30: Issue price | Q30: Issue price | R30: Issue price | S30: Issue price | T30: Issue price | U30: Issue price | V30: Issue price | W30: Issue price | X30: Issue price | Y30: Issue price | Z30: Issue price | AA30: Issue price | AB30: Issue price | AC30: Subscription end date | AD30: Issue price | AE30: Issue price | AF30: Issue price | AG30: Issue price | AH30: Issue price | AI30: Issue price | AJ30: Issue price | AK30: Subscription end date | AL30: Subscription end date | AM30: Issue price | AN30: Issue price | AO30: Issue price | AP30: Issue price
B31: Issue date | C31: Issue date | D31: Issue date | E31: Issue date | F31: Issue date | G31: Issue date | H31: Issue date | I31: Issue date | J31: Issue date | K31: Issue date | L31: Issue date | M31: Issue date | N31: Issue date | O31: Issue date | P31: Issue date | Q31: Issue date | R31: Issue date | S31: Issue date | T31: Issue date | U31: Issue date | V31: Issue date | W31: Issue date | X31: Issue date | Y31: Issue date | Z31: Issue date | AA31: Issue date | AB31: Issue date | AC31: Issue price | AD31: Issue date | AE31: Issue date | AF31: Issue date | AG31: Issue date | AH31: Issue date | AI31: Issue date | AJ31: Issue date | AK31: Issue price | AL31: Issue price | AM31: Issue date | AN31: Issue date | AO31: Issue date | AP31: Issue date
B32: Nominal amount + currency | C32: Nominal amount + currency | D32: Nominal amount + currency | E32: Nominal amount + currency | F32: Nominal amount + currency | G32: Nominal amount + currency | H32: Nominal amount + currency | I32: Nominal amount + currency | J32: Nominal amount + currency | K32: Nominal amount + currency | L32: Nominal amount + currency | M32: Nominal amount + currency | N32: Nominal amount + currency | O32: Nominal amount + currency | P32: Nominal amount + currency | Q32: Nominal amount + currency | R32: Nominal amount + currency | S32: Nominal amount | T32: Nominal amount + currency | U32: Nominal amount + currency | V32: Nominal amount + currency | W32: Nominal amount + currency | X32: Nominal amount + currency | Y32: Nominal amount + currency | Z32: Nominal amount + currency | AA32: Nominal amount + currency | AB32: Nominal amount + currency | AC32: Issue date | AD32: Nominal amount + currency | AE32: Nominal amount + currency | AF32: Nominal amount + currency | AG32: Nominal amount + currency | AH32: Nominal amount + currency | AI32: Nominal amount + currency | AJ32: Nominal amount + currency | AK32: Issue date | AL32: Issue date | AM32: Nominal amount + currency | AN32: Nominal amount + currency | AO32: Nominal amount + currency | AP32: Nominal amount + currency
B33: Participation ratio | C33: Participation ratio | D33: Coupon | E33: Participation ratio | F33: Participation ratio | G33: Interest margin per annum | H33: Participation ratio | I33: Participation ratio 1 | J33: Participation ratio | K33: Participation ratio | L33: Coupon | M33: Coupon | N33: Fixed interest per annum | O33: Participation ratio | P33: Participation ratio | Q33: Participation ratio | R33: Participation ratio 1 | S33: Lock-in level(s) | T33: Participation ratio | U33: Interest margin per annum | V33: Participation ratio | W33: Fixed interest per annum | X33: Participation ratio | Y33: Coupon | Z33: Participation ratio | AA33: Participation ratio | AB33: Participation ratio | AC33: Nominal amount + currency | AD33: Coupon | AE33: Participation ratio | AF33: Adjusted nominal amount | AG33: Coupon 1 | AH33: Participation ratio | AI33: Participation ratio | AJ33: Participation ratio | AK33: Nominal amount + currency | AL33: Nominal amount + currency | AM33: Participation ratio | AN33: Interest margin per annum | AO33: Participation ratio | AP33: Participation ratio
B34: Barrier | C34: Valuation date(s) | D34: Valuation date(s) | E34: Valuation date(s) | F34: Performance cap | G34: Reference rate | H34: Performance cap | I34: Participation ratio 2 | J34: Barrier | K34: Barrier | L34: Barrier | M34: Barrier | N34: Barrier | O34: Performance cap | P34: Valuation date(s) | Q34: Barrier | R34: Participation ratio 2 | S34: Participation ratio | T34: Barrier | U34: Reference rate | V34: Coupon | W34: Barrier | X34: Performance cap | Y34: Barrier | Z34: Coupon | AA34: Coupon | AB34: Currency exposure | AC34: Coupon | AD34: Interest payment date(s) | AE34: Fixed interest per annum | AF34: Fixed interest per annum | AG34: Coupon 2 | AH34: Redemption date | AI34: Maximum loss | AJ34: Redemption date | AK34: Participation ratio | AL34: Coupon | AM34: Maximum loss | AN34: Reference rate | AO34: Performance cap | AP34: Underlying asset 1
B35: Valuation date(s) | C35: Redemption date | D35: Redemption date | E35: Redemption date | F35: Barrier | G35: Barrier | H35: Redemption date | I35: Barrier | J35: Currency exposure | K35: Valuation date(s) | L35: Initial valuation date | M35: Valuation date(s) | N35: Interest payment date(s) | O35: Valuation date(s) | P35: Redemption date | Q35: Valuation date(s) | R35: Barrier | S35: Barrier | T35: Underlying asset 1 | U35: Barrier | V35: Barrier | W35: Initial valuation date | X35: Barrier | Y35: Valuation date(s) | Z35: Barrier | AA35: Barrier | AB35: Valuation date(s) | AC35: Valuation date(s) | AD35: Valuation date(s) | AE35: Interest payment date(s) | AF35: Barrier | AG35: Barrier | AI35: Currency exposure | AK35: Performance floor | AL35: Redemption date | AM35: Currency exposure | AN35: Barrier | AO35: Currency exposure | AP35: Underlying asset 2
B36: Redemption date | F36: Valuation date(s) | G36: Interest payment date(s) | I36: Valuation date(s) | J36: Valuation date(s) | K36: Redemption date | L36: End valuation date(s) | M36: Redemption date | N36: Valuation date(s) | O36: Redemption date | Q36: Redemption date | R36: Valuation date(s) | S36: Valuation date(s) | T36: Underlying asset 2 | U36: Initial valuation date | V36: Valuation date(s) | W36: End valuation date(s) | X36: Currency exposure | Y36: Redemption date | Z36: Currency exposure | AA36: Valuation date(s) | AB36: Redemption date | AC36: Redemption date | AD36: Redemption date | AE36: Redemption date | AF36: Interest payment date(s) | AG36: Valuation date(s) | AI36: Redemption date | AK36: Performance cap | AM36: Redemption date | AN36: Interest payment date(s) | AO36: Redemption date | AP36: Valuation date(s)
F37: Redemption date | G37: Valuation date(s) | I37: Redemption date | J37: Redemption date | L37: Redemption date | N37: Redemption date | R37: Redemption date | S37: Redemption date | T37: Valuation date(s) | U37: End valuation date(s) | V37: Redemption date | W37: Interest payment date(s) | X37: Initial valuation date | Z37: Valuation date(s) | AA37: Redemption date | AF37: Initial valuation date | AG37: Redemption date | AH37: Initial valuation date | AJ37: Initial valuation date | AK37: Target redemption amount | AN37: Valuation date(s) | AP37: Redemption date
G38: Redemption date | T38: Redemption date | U38: Interest payment date(s) | W38: Redemption date | X38: End valuation date(s) | Z38: Redemption date | AD38: Initial valuation date | AF38: End valuation date(s) | AH38: Valuation date(s) | AJ38: Valuation date(s) | AK38: Redemption date | AL38: Initial valuation date | AN38: Redemption date
B39: Initial valuation date | J39: Initial valuation date | U39: Redemption date | X39: Redemption date | AE39: Initial valuation date | AF39: Redemption date | AL39: Valuation date(s)
H40: Initial valuation date | J40: FX valuation start date | Y40: Initial valuation date | AA40: Initial valuation date | AE40: Valuation date(s) | AG40: Initial valuation date | AK40: Initial valuation date | AO40: Initial valuation date | AP40: Initial valuation date
C41: Initial valuation date | D41: Initial valuation date | E41: Initial valuation date | F41: Initial valuation date | G41: Initial valuation date | H41: Valuation date(s) | I41: Initial valuation date | J41: FX valuation end date | K41: Initial valuation date | M41: Initial valuation date | N41: Initial valuation date | O41: Initial valuation date | P41: Initial valuation date | Q41: Initial valuation date | R41: Initial valuation date | S41: Initial valuation date | T41: Initial valuation date | V41: Initial valuation date | AB41: Initial valuation date | AK41: Valuation date(s) | AN41: Initial valuation date | AO41: Valuation date(s)
W42: Initial valuation date | X42: Initial valuation date | Z42: Initial valuation date | AB42: FX valuation start date | AC42: Initial valuation date | AI42: Initial valuation date | AM42: Initial valuation date
X43: FX valuation start date | Z43: FX valuation start date | AB43: FX valuation end date | AI43: Valuation date(s) | AM43: Valuation date(s)
X44: FX valuation end date | Z44: FX valuation end date | AI44: FX valuation start date | AM44: FX valuation start date
AI45: FX valuation end date | AM45: FX valuation end date

Sheet Minimum redemption
B1: SE0005136967 | C1: XS0953294203 | D1: SE0004873461 | E1: SE0004545648 | F1: SE0006599684 | G1: XS1283654785 | H1: SE0005990975 | I1: SE0005650488 | K1: XS1377459257 | L1: XS1405113744 | M1: XS0994742624 | N1: XS0757051155 | O1: SE0006599569 | P1: SE0005650462 | Q1: SE0005281789 | R1: FI4000090766 | S1: FI4000041116
B2: Minimum redemption 1 | C2: Minimum redemption 2 | D2: Minimum redemption 3 | E2: Minimum redemption 4 | F2: Minimum redemption 5 | G2: Minimum redemption 6 | H2: Minimum redemption 7 | I2: Minimum redemption 8 | J2: Minimum redemption 9 | K2: Minimum redemption 10 | L2: Minimum redemption 11 | M2: Minimum redemption 12 | N2: Minimum redemption 13 | O2: Minimum redemption 14 | P2: Minimum redemption 15 | Q2: Minimum redemption 16 | R2: Minimum redemption 17 | S2: Minimum redemption 18
A3: Level 1 | B3: Multi underlying | C3: Single underlying | D3: Single underlying, TOM | E3: Single underlying, TOM | F3: Single underlying | G3: Multi underlying | H3: Multi underlying | I3: Single underlying, TOM | J3: Single underlying | K3: Multi underlying | L3: Single underlying | M3: Multi underlying | N3: Multi underlying (relative difference between two underlying assets) | O3: Single underlying | P3: Multi underlying | Q3: Single underlying | R3: Single underlying FX (one currency pair) | S3: Multi underlying
A4: Level 2 | B4: Participation ratio | C4: Participation ratio | D4: Participation ratio | E4: Participation ratio | F4: Participation ratio | G4: Participation ratio | H4: Participation ratio | I4: Participation ratio | J4: Participation ratio | K4: Participation ratio | L4: Participation ratio | M4: Participation ratio | N4: Floating interest for the forthcoming interest payment dates | O4: Participation ratio | P4: Participation ratio | Q4: Participation ratio | R4: Participation ratio | S4: Participation ratio
A5: Level 3 | B5: Flexo | C5: Capped | D5: Quanto | E5: Guaranteed fixed coupon | F5: Quanto | G5: Quanto | H5: Strike = 90 % | I5: Quanto | J5: Quanto | K5: Capped | L5: Quanto | M5: Capped | N5: Floor and cap | O5: Flexo | P5: Strike = 90 % | Q5: Strike = 90 % | R5: Capped | S5: Quanto
A6: Level 4 | C6: Quanto | E6: Quanto | H6: Flexo | K6: Quanto | M6: Quanto | P6: Quanto | Q6: Flexo | R6: Quanto
A7: Short description | B7: This is a partly capital protected note with more than one underlying assets in a basket. The positive return is affected by currency fluctuations. | C7: This is a partly capital protected note with one underlying asset. The performance of the underlying asset has a cap. | D7: This is a partly capital protected note with one underlying asset. The performance of the underlying asset is determined by a predefined strategy – turn of the month. Turn of the month means that the note is exposed to the underlying asset only during a predefined number of days per month. Return is calculated as nominal amount + (nominal amount x performance of the underlying asset x participation ratio). | E7: This is a partly capital protected note with one underlying asset. The performance of the underlying asset is determined by a predefined strategy – turn of the month. Turn of the month means that the note is exposed to the underlying asset only during a predefined number of days per month. On each interest payment date, the note will pay a fixed coupon, calculated on the nominal amount. | F7: This is a partly capital protected note with one underlying asset. | G7: This is a partly capital protected note with more than one underlying asset. | H7: This is a partly capital protected note with more than one underlying asset. Strike = 90 %. The positive return is affected by currency fluctuations. | I7: This is a partly capital protected note with one underlying asset. The performance of the underlying asset is determined by a predefined strategy – turn of the month. Turn of the month means that the note is exposed to the underlying asset only during a predefined number of days per month. Return is calculated as minimum redemption amount + (nominal amount x performance of the underlying asset x participation ratio). | J7: This is a partly capital protected note with one underlying asset. | K7: This is a partly capital protected note with more than one underlying asset in a basket. The performance of the underlying basket has a cap. | L7: This is a partly capital protected note with one underlying asset. If the underlying asset has a positive performance, the note will pay the nominal amount plus the nominal amount multiplied by the performance of the underlying asset multiplied by the participation ratio, on the redemption date. If the underlying asset has an unfavourable performance, the note will pay the highest of the minimum redemption amount, and the nominal amount reduced by the negative performance of the underlying asset, on the redemption date. | M7: This is a partly capital protected note with more than one underlying asset in a basket. The performance of the underlying basket has a cap. | N7: This is a partly capital protected note linked to the relative difference between two underlying assets. The note will pay a floating coupon, calculated as an interest rate spread. The interest rate spread has a floor and a cap. On the redemption date, the note will pay the minimum redemption amount. | O7: This is a partly capital protected note with one underlying asset. The positive return is affected by currency fluctuations. | P7: This is a partly capital protected note with more than one underlying asset. Strike = 90 %. | Q7: This is a partly capital protected note with one underlying asset. Strike = 90 %. The positive return is affected by currency fluctuations. | R7: This is a partly capital protected note with one underlying asset (currency pair = basket short). The performance of the underlying asset has a cap. | S7: This is a partly capital protected note with one underlying asset. If the underlying asset has a positive performance, the note will pay the nominal amount plus the nominal amount multiplied by the performance of the underlying asset multiplied by the participation ratio, on the redemption date. If the underlying asset has an unfavourable performance, the note will pay the nominal amount reduced by 50 percentage of the negative performance of the underlying asset, on the redemption date.
A8: EUSIPA-code | B8: 1330 | C8: 1240 | D8: 1330 | E8: 1320 | F8: 1330 | G8: 1330 | H8: 1330 | I8: 1330 | J8: 1330 | K8: 1240 | L8: 1330 | M8: 1240 | N8: 1240 | O8: 1330 | P8: 1330 | Q8: 1330 | R8: 1240 | S8: 1330
B9: FixedRedemption | D9: Put1
B10: Call1 | D10: Put2
A14: Type | B14: 1 b according to the MiFID (legal form?) | C14: 1 b according to the MiFID (legal form?) | D14: 1 b according to the MiFID (legal form?) | E14: 1 b according to the MiFID (legal form?) | F14: 1 b according to the MiFID (legal form?) | G14: 1 b according to the MiFID (legal form?) | H14: 1 b according to the MiFID (legal form?) | I14: 1 b according to the MiFID (legal form?) | J14: 1 b according to the MiFID (legal form?) | K14: 1 b according to the MiFID (legal form?) | L14: 1 b according to the MiFID (legal form?) | M14: 1 b according to the MiFID (legal form?) | N14: 1 b according to the MiFID (legal form?) | O14: 1 b according to the MiFID (legal form?) | P14: 1 b according to the MiFID (legal form?) | Q14: 1 b according to the MiFID (legal form?) | R14: 1 b according to the MiFID (legal form?) | S14: 1 b according to the MiFID (legal form?)
B15: Outperformance Bonus Certificate | C15: Capped Outperformance Certificate | D15: Outperformance Bonus Certificate | E15: Bonus Certificate | F15: Outperformance Bonus Certificate | G15: Outperformance Bonus Certificate | H15: Outperformance Bonus Certificate | I15: Outperformance Bonus Certificate | J15: Outperformance Bonus Certificate | K15: Capped Outperformance Certificate | L15: Outperformance Bonus Certificate | M15: Capped Outperformance Certificate | N15: Capped Outperformance Certificate | O15: Outperformance Bonus Certificate | P15: Outperformance Bonus Certificate | Q15: Outperformance Bonus Certificate | R15: Capped Outperformance Certificate | S15: Outperformance Bonus Certificate
B16: Underlying asset(s) (initial price) | C16: Underlying asset(s) (initial price) | D16: Underlying asset(s) (initial price) | E16: Underlying asset(s) (initial price) | F16: Underlying asset(s) (initial price) | G16: Underlying asset(s) (initial price) | H16: Underlying asset(s) (initial price) | I16: Underlying asset(s) (initial price) | J16: Underlying asset(s) (initial price) | K16: Underlying asset(s) (initial price) | L16: Underlying asset(s) (initial price) | M16: Underlying asset(s) (initial price) | N16: Underlying asset(s) (initial price) | O16: Underlying asset(s) (initial price) | P16: Underlying asset(s) (initial price) | Q16: Underlying asset(s) (initial price) | R16: Underlying asset(s) (initial price) | S16: Underlying asset(s) (initial price)
A17: How the investment works | B17: The objective is to benefit from a rising market, and at the same time have the protection of getting back the minimum redemption amount if the market is falling. | C17: The objective is to benefit from a rising market, and at the same time have the protection of getting back the minimum redemption amount if the market is falling. | D17: The objective is to benefit from a rising market, and at the same time have the protection of getting back the minimum redemption amount if the market is falling. | E17: The objective is to invest in a note that will pay fixed coupons, benefit from a rising market and at the same time have the protection of getting back the minimum redemption amount if the market is falling. | F17: The objective is to benefit from a rising market, and at the same time have the protection of getting back the minimum redemption amount if the market is falling. | G17: The objective is to benefit from a rising market, and at the same time have the protection of getting back the minimum redemption amount if the market is falling. | H17: The objective is to benefit from a rising market, and at the same time have the protection of getting back the minimum redemption amount if the market is falling. | I17: The objective is to benefit from a rising market, and at the same time have the protection of getting back the minimum redemption amount if the market is falling. | J17: The objective is to benefit from a rising market, and at the same time have the protection of getting back the minimum redemption amount if the market is falling. | K17: The objective is to benefit from a rising market, and at the same time have the protection of getting back the minimum redemption amount if the market is falling. | L17: The objective is to benefit from a rising market, and at the same time have the protection of getting back the minimum redemption amount if the market is falling. | M17: The objective is to benefit from a rising market, and at the same time have the protection of getting back the minimum redemption amount if the market is falling. | N17: The objective is to benefit from the relative difference between two underlying assets, and at the same time have the protection of getting back the minimum redemption amount if the market is falling. | O17: The objective is to benefit from a rising market, and at the same time have the protection of getting back the minimum redemption amount if the market is falling. | P17: The objective is to benefit from a rising market, and at the same time have the protection of getting back the minimum redemption amount if the market is falling. | Q17: The objective is to benefit from a rising market, and at the same time have the protection of getting back the minimum redemption amount if the market is falling. | R17: The objective is to benefit from a rising market, and at the same time have the protection of getting back the minimum redemption amount if the market is falling. | S17: The objective is to benefit from a rising market, and at the same time have the protection of getting back the minimum redemption amount if the market is falling.
B18: The return of the investment depends on the performance of a basket of underlying assets during the lifetime of the investment. | C18: The return of the investment depends on the performance of the underlying asset during the lifetime of the investment. | D18: The return of the investment depends on the performance of the underlying asset during the lifetime of the investment. | E18: The return of the investment depends on the performance of the underlying asset during the lifetime of the investment. | F18: The return of the investment depends on the performance of the underlying asset during the lifetime of the investment. | G18: The return of the investment depends on the performance of a basket of underlying assets during the lifetime of the investment. | H18: The return of the investment depends on the performance of a basket of underlying assets during the lifetime of the investment. | I18: The return of the investment depends on the performance of the underlying asset during the lifetime of the investment. | J18: The return of the investment depends on the performance of the underlying asset during the lifetime of the investment. | K18: The return of the investment depends on the performance of a basket of underlying assets during the lifetime of the investment. | L18: The return of the investment depends on the performance of the underlying asset during the lifetime of the investment. | M18: The return of the investment depends on the performance of a basket of underlying assets during the lifetime of the investment. | N18: The return of the investment depends on the relative difference between two underlying assets during the lifetime of the investment. | O18: The return of the investment depends on the performance of the underlying asset during the lifetime of the investment. | P18: The return of the investment depends on the performance of a basket of underlying assets during the lifetime of the investment. | Q18: The return of the investment depends on the performance of the underlying asset an underlying assets during the lifetime of the investment. | R18: The return of the investment depends on the performance of the underlying asset during the lifetime of the investment. | S18: The return of the investment depends on the performance of a basket of underlying assets during the lifetime of the investment.
B19: If the basket has had a positive performance, the note will pay the minimum redemption amount plus the nominal amount multiplied by the performance of the basket multiplied by the participation ratio, on the redemption date. Currency fluctuations will also affect the return of the investment. | C19: If the underlying asset has had a positive performance, the note will pay the minimum redemption amount plus the nominal amount multiplied by the performance of the underlying asset multiplied by the participation ratio, on the redemption date. When calculating the performance, the performance has had a cap. | D19: If the underlying asset has had a positive performance, the note will pay the nominal amount plus the nominal amount multiplied by the performance of the underlying asset multiplied by the participation ratio, on the redemption date. | E19: The note will pay a fixed interest, calculated on the nominal amount, on every interest payment date. | F19: If the underlying asset has had a positive performance, the note will pay the minimum redemption amount plus the nominal amount multiplied by the performance of the underlying asset multiplied by the participation ratio, on the redemption date. | G19: If the basket has had a positive performance, the note will pay the nominal amount plus the nominal amount multiplied by the performance of the underlying basket multiplied by the participation ratio, on the redemption date. | H19: If the basket has had a positive performance, the note will pay the minimum redemption amount plus the nominal amount multiplied by the performance of the basket multiplied by the participation ratio, on the redemption date. When calculating the performance of the basket, the performance will always be 10 percentage points higher than the actual performance of the underlying basket. Currency fluctuations will also affect the return of the investment. | I19: If the underlying asset has had a positive performance, the note will pay the minimum redemption amount plus the nominal amount multiplied by the performance of the underlying asset multiplied by the participation ratio, on the redemption date. | J19: If the underlying asset has had a positive performance, the note will pay the minimum redemption amount plus the nominal amount multiplied by the performance of the underlying asset multiplied by the participation ratio, on the redemption date. | K19: If the basket has had a positive performance, the note will pay the nominal amount plus the nominal amount multiplied by the performance of the basket multiplied by the participation ratio, on the redemption date. When calculating the performance of the basket, it will be equal to the lowest of the basket performance and the performance cap. | L19: If the underlying asset has had a positive performance, the note will pay the nominal amount plus the nominal amount multiplied by the performance of the underlying asset multiplied by the participation ratio, on the redemption date. | M19: If the basket has had a positive performance, the note will pay the minimum redemption amount plus the nominal amount multiplied by the performance of the basket multiplied by the participation ratio, on the redemption date. When calculating the performance of the underlying basket, it will be equal to the lowest of the basket performance and the performance cap. | N19: If, on a valuation date, the relative difference between the underlying assets is within a predefined interval, the note will pay the nominal amount multiplied with the participation ratio multiplied with the relative difference between the underlying assets on the next interest payment date. | O19: If the underlying asset has had a positive performance, the note will pay the minimum redemption amount plus the nominal amount multiplied by the performance of the underlying asset multiplied by the participation ratio, on the redemption date. Currency fluctuations will also affect the return of the investment. | P19: If the basket has had a positive performance, the note will pay the minimum redemption amount plus the nominal amount multiplied by the performance of the basket multiplied by the participation ratio, on the redemption date. When calculating the performance of the basket, the performance will always be 10 percentage points higher than the actual performance of the basket. | Q19: If the underlying asset has had a positive performance, the note will pay the minimum redemption amount plus the nominal amount multiplied by the performance of the underlying asset multiplied by the participation ratio, on the redemption date. When calculating the performance of the underlying asset, the performance will always be 10 percentage points higher than the actual performance of the underlying asset. Currency fluctuations will also affect the return of the investment. | R19: If the underlying asset has had a positive performance, the note will pay the nominal amount plus the nominal amount multiplied by the performance of the underlying asset multiplied by the participation ratio, on the redemption date. When calculating the performance of the underlying asset, the performance has had a cap. | S19: If the basket has had a positive performance, the note will pay the nominal amount plus the nominal amount multiplied by the performance of the underlying asset multiplied by the participation ratio, on the redemption date.
B20: If the basket has had a negative performance, the note will pay the minimum redemption amount on the redemption date. | C20: If the underlying asset has had a negative performance, the note will pay the minimum redemption amount on the redemption date. | D20: The performance of the underlying asset is determined by a predefined strategy – turn of the month. Turn of the month means that the note is exposed to the underlying asset only during a predefined number of days per month. | E20: If the underlying asset has had a positive performance, the note will pay the minimum redemption amount plus the nominal amount multiplied by the performance of the underlying asset multiplied by the participation ratio, on the redemption date. | F20: If the underlying asset has had a negative performance, the note will pay the minimum redemption amount on the redemption date. | G20: If the basket has had a negative performance, the note will pay the highest of the minimum redemption amount and the nominal amount reduced by the negative performance of the underlying basket on the redemption date. | H20: If the basket has had a negative performance (actual performance of minus 10 percent or more), the note will pay the minimum redemption amount on the redemption date. | I20: The performance of the underlying asset is determined by a predefined strategy – turn of the month. Turn of the month means that the note is exposed to the underlying asset only during a predefined number of days per month. | J20: If the underlying asset has had a negative performance, the note will pay the minimum redemption amount on the redemption date. | K20: If the basket has had a negative performance, the note will pay the highest of the minimum redemption amount and the nominal amount reduced by the negative performance of the basket on the redemption date. | L20: If the underlying asset has had a negative performance, the note will pay the highest of the minimum redemption amount and the nominal amount reduced by the negative performance of the underlying asset on the redemption date. | M20: If the basket has had a negative performance, the note will pay the minimum redemption amount on the redemption date. | N20: If, on a valuation date, the relative difference between the underlying assets is higher than a predefined interval, the note will pay the maximum coupon on the next interest payment date. | O20: If the underlying asset has had a negative performance, the note will pay the minimum redemption amount on the redemption date. | P20: If the basket has had an negative performance (actual performance of minus 10 percent or more), the note will pay the minimum redemption amount on the redemption date. | Q20: If the underlying asset has had an negative performance (actual performance of minus 10 percent or more), the note will pay the minimum redemption amount on the redemption date. | R20: If the underlying asset has had a negative performance, the note will pay the higher of the minimum redemption amount, and the nominal amount reduced by the negative performance of the underlying asset, on the redemption date. | S20: If the basket has had a negative performance, the note will pay the nominal amount plus the nominal amount multiplied by the negative performance of the basket multiplied by the downside participation ratio on the redemption date.
D21: If the underlying asset has had a negative performance, the note will pay the highest of the minimum redemption amount and the nominal amount reduced by the negative performance of the underlying asset on the redemption date. | E21: The performance of the underlying asset is determined by a predefined strategy – turn of the month. Turn of the month means that the note is exposed to the underlying asset only during a predefined number of days per month. | I21: If the underlying asset has had a negative performance, the note will pay the minimum redemption amount on the redemption date. | N21: If, on a valuation date, the relative difference between the underlying assets is lower than a predefined interval, no floating interest will be paid on the next interest payment date.
E22: If the underlying asset has had a negative performance, the note will pay the minimum redemption amount on the redemption date. | N22: The note will pay the minimum redemption amount on the redemption date.
A24: Key figures: | B24: Minimum subscription amount | C24: Minimum subscription amount | D24: Minimum subscription amount | E24: Minimum subscription amount | F24: Minimum subscription amount | G24: Minimum subscription amount | H24: Minimum subscription amount | I24: Minimum subscription amount | J24: Minimum subscription amount | K24: Minimum subscription amount | L24: Minimum subscription amount | M24: Minimum subscription amount | N24: Minimum subscription amount | O24: Minimum subscription amount | P24: Minimum subscription amount | Q24: Minimum subscription amount | R24: Minimum subscription amount | S24: Minimum subscription amount
B25: Subscription end date | C25: Subscription end date | D25: Subscription end date | E25: Subscription end date | F25: Subscription end date | G25: Subscription end date | H25: Subscription end date | I25: Subscription end date | J25: Subscription end date | K25: Subscription end date | L25: Subscription end date | M25: Subscription end date | N25: Subscription end date | O25: Subscription end date | P25: Subscription end date | Q25: Subscription end date | R25: Subscription end date | S25: Subscription end date
B26: Issue price | C26: Issue price | D26: Issue price | E26: Issue price | F26: Issue price | G26: Issue price | H26: Issue price | I26: Issue price | J26: Issue price | K26: Issue price | L26: Issue price | M26: Issue price | N26: Issue price | O26: Issue price | P26: Issue price | Q26: Issue price | R26: Issue price | S26: Issue price
B27: Issue date | C27: Issue date | D27: Issue date | E27: Issue date | F27: Issue date | G27: Issue date | H27: Issue date | I27: Issue date | J27: Issue date | K27: Issue date | L27: Issue date | M27: Issue date | N27: Issue date | O27: Issue date | P27: Issue date | Q27: Issue date | R27: Issue date | S27: Issue date
B28: Nominal amount + currency | C28: Nominal amount + currency | D28: Nominal amount + currency | E28: Nominal amount + currency | F28: Nominal amount + currency | G28: Nominal amount + currency | H28: Nominal amount + currency | I28: Nominal amount + currency | J28: Nominal amount + currency | K28: Nominal amount + currency | L28: Nominal amount + currency | M28: Nominal amount + currency | N28: Nominal amount + currency | O28: Nominal amount + currency | P28: Nominal amount + currency | Q28: Nominal amount + currency | R28: Nominal amount + currency | S28: Nominal amount + currency
B29: Minimum redemption amount | C29: Minimum redemption amount | D29: Minimum redemption amount | E29: Minimum redemption amount | F29: Minimum redemption amount | G29: Minimum redemption amount | H29: Minimum redemption amount | I29: Minimum redemption amount | J29: Minimum redemption amount | K29: Minimum redemption amount | L29: Minimum redemption amount | M29: Minimum redemption amount | N29: Minimum redemption amount | O29: Minimum redemption amount | P29: Minimum redemption amount | Q29: Minimum redemption amount | R29: Minimum redemption amount | S29: Participation ratio
B30: Participation ratio | C30: Participation ratio | D30: Participation ratio | E30: Participation ratio | F30: Participation ratio | G30: Participation ratio | H30: Participation ratio | I30: Participation ratio | J30: Participation ratio | K30: Participation ratio | L30: Participation ratio | M30: Participation ratio | N30: Participation ratio | O30: Participation ratio | P30: Participation ratio | Q30: Participation ratio | R30: Participation ratio | S30: Downside participation ratio
B31: Currency exposure | C31: Performance cap | D31: Redemption date | E31: Fixed interest per annum | F31: Redemption date | G31: Redemption date | H31: Currency exposure | I31: Redemption date | J31: Redemption date | K31: Performance cap | L31: Redemption date | M31: Performance cap | N31: Performance floor | O31: Currency exposure | P31: Redemption date | Q31: Currency exposure | R31: Performance cap | S31: Redemption date
B32: Redemption date | C32: Redemption date | E32: Interest payment date(s) | H32: Redemption date | K32: Redemption date | M32: Redemption date | N32: Performance cap | O32: Redemption date | Q32: Redemption date | R32: Redemption date
E33: Redemption date | N33: Maximum coupon
N34: Interest payment date(s)
B35: Initial valuation date | C35: Initial valuation date | D35: Initial valuation date | E35: Initial valuation date | F35: Initial valuation date | G35: Initial valuation date | H35: Initial valuation date | I35: Initial valuation date | J35: Initial valuation date | K35: Initial valuation date | L35: Initial valuation date | M35: Initial valuation date | N35: Valuation date(s) | S35: Initial valuation date
B36: Valuation date(s) | C36: Valuation date(s) | D36: Valuation date(s) | E36: Valuation date(s) | F36: Valuation date(s) | G36: Valuation date(s) | H36: Valuation date(s) | I36: Valuation date(s) | J36: Valuation date(s) | K36: Valuation date(s) | L36: Valuation date(s) | M36: Valuation date(s) | N36: Redemption date | Q36: Initial valuation date | R36: Initial valuation date | S36: Valuation date(s)
B37: FX valuation start date | H37: FX valuation start date | Q37: Valuation date(s) | R37: Valuation date(s)
B38: FX valuation end date | H38: FX valuation end date | N38: Initial valuation date | O38: Initial valuation date | P38: Initial valuation date | Q38: FX valuation start date
O39: Valuation date(s) | P39: Valuation date(s) | Q39: FX valuation end date
O40: FX valuation start date
O41: FX valuation end date

Sheet Tabelle1
A1: Upside | B1: Payout | D1: Downside | E1: Payout
